{
  "title": "Wolf Pack 5",
  "type": "Animatronic Shows",
  "tags": [
    "ShowBiz Pizza Place"
  ],
  "startDate": "",
  "endDate": "",
  "contributors": [
    "Sponch man",
    "Himitsu",
    "sudo trans --pony",
    "Anonymous",
    "Anonymous",
    "Anonymous",
    "Zlblosser23",
    "Anonymous",
    "Anonymous",
    "Anonymous",
    "Anonymous",
    "Anonymous",
    "Stripes",
    "Lelmaster"
  ],
  "citations": [
    "<a href=\"https://www.youtube.com/watch?v=KFkG-FhtP38&lc=Ugy-GIDH3xQUzKqoSd54AaABAg.9H8RYctWvdU9I3S36nwa8O\">https://www.youtube.com/watch?v=KFkG-FhtP38&lc=Ugy-GIDH3xQUzKqoSd54AaABAg.9H8RYctWvdU9I3S36nwa8O</a>",
    "<a href=\"http://www.showbizpizza.com/info/articles/spp/spp_80kansascity.pdf\">http://www.showbizpizza.com/info/articles/spp/spp_80kansascity.pdf</a>",
    "<a href=\"https://youtu.be/kLMRKaF31ko?t=1978\">https://youtu.be/kLMRKaF31ko?t=1978</a>",
    "<a href=\"https://m.facebook.com/permalink.php?story_fbid=10150275198662312&id=101506232311\">https://m.facebook.com/permalink.php?story_fbid=10150275198662312&id=101506232311</a>",
    "<a href=\"https://www.showbizpizza.com/review/rae/1982_abbeyroad.html\">https://www.showbizpizza.com/review/rae/1982_abbeyroad.html</a>",
    "<a href=\"http://www.showbizpizza.com/photos/misc/wolfpack5/04.jpg\">http://www.showbizpizza.com/photos/misc/wolfpack5/04.jpg</a>",
    "<a href=\"http://www.showbizpizza.com/history/index.html\">http://www.showbizpizza.com/history/index.html</a>",
    "<a href=\"https://youtu.be/gTmhS6hcY-A?t=1342\">https://youtu.be/gTmhS6hcY-A?t=1342</a>",
    "<a href=\"http://www.showbizpizza.com/photos/misc/wolfpack5/02.jpg\">http://www.showbizpizza.com/photos/misc/wolfpack5/02.jpg</a>",
    "<a href=\"https://www.showbizpizza.com/radio/archive.html\">https://www.showbizpizza.com/radio/archive.html</a>",
    "<a href=\"https://www.youtube.com/watch?v=z_azKuOjCCs\">https://www.youtube.com/watch?v=z_azKuOjCCs</a>",
    "<a href=\"https://stanceworks.com/forums/showthread.php?75439-Not-a-mini-truck-Mega-truck&p=1473077#post1473077\">https://stanceworks.com/forums/showthread.php?75439-Not-a-mini-truck-Mega-truck&p=1473077#post1473077</a>",
    "<a href=\"https://en.wikipedia.org/wiki/Expo_67\">https://en.wikipedia.org/wiki/Expo_67</a>",
    "<a href=\"https://www.newspapers.com/article/richmond-times-dispatch-wp5-opens-at-kin/141674898/\">https://www.newspapers.com/article/richmond-times-dispatch-wp5-opens-at-kin/141674898/</a>",
    "<a href=\"https://parkfans.net/threads/livingstons.3570/\">https://parkfans.net/threads/livingstons.3570/</a>",
    "<a href=\"https://www.instagram.com/p/CDd2kwPnsOF/\">https://www.instagram.com/p/CDd2kwPnsOF/</a>",
    "<a href=\"https://delriorec.blogspot.com/2012/04/los-munecos-cantores-del-italpark.html\">https://delriorec.blogspot.com/2012/04/los-munecos-cantores-del-italpark.html</a>",
    "<a href=\"https://www.youtube.com/watch?v=K1bTMDcu7DE&lc=UgyCNIrcP46KcF1Bfbx4AaABAg\">https://www.youtube.com/watch?v=K1bTMDcu7DE&lc=UgyCNIrcP46KcF1Bfbx4AaABAg</a>",
    "<a href=\"https://www.tapatalk.com/groups/retro_pizza_zone/the-wolf-pack-5-at-fame-city-t6280.html\">https://www.tapatalk.com/groups/retro_pizza_zone/the-wolf-pack-5-at-fame-city-t6280.html</a>",
    "<a href=\"https://www.aphan.ca/pyramidplace.html\">https://www.aphan.ca/pyramidplace.html</a>",
    "<a href=\"https://www.facebook.com/100388312150125/photos/a.252910466897908/370288795160074/\">https://www.facebook.com/100388312150125/photos/a.252910466897908/370288795160074/</a>",
    "<a href=\"https://www.instagram.com/p/CPWDxgNnkNo/\">https://www.instagram.com/p/CPWDxgNnkNo/</a>",
    "<a href=\"https://www.aphan.ca/images/pyramid1.jpg\">https://www.aphan.ca/images/pyramid1.jpg</a>",
    "<a href=\"https://www.instagram.com/p/CZS6mAKJM-7/\">https://www.instagram.com/p/CZS6mAKJM-7/</a>",
    "<a href=\"https://www.youtube.com/watch?v=iNAixJQ3jeA&lc=Ugw3U1Gyp4mOkbIkI4x4AaABAg\">https://www.youtube.com/watch?v=iNAixJQ3jeA&lc=Ugw3U1Gyp4mOkbIkI4x4AaABAg</a>",
    "<a href=\"http://www.showbizpizza.com/info/promo/cei/cei_1980promo.pdf\">http://www.showbizpizza.com/info/promo/cei/cei_1980promo.pdf</a>",
    "<a href=\"https://web.archive.org/web/20110524063531/http://www.okamotos.co.jp/cotarog/sonota.pdf\">https://web.archive.org/web/20110524063531/http://www.okamotos.co.jp/cotarog/sonota.pdf</a>",
    "<a href=\"http://www.showbizpizza.com/photos/misc/wolfpack5/03.jpg\">http://www.showbizpizza.com/photos/misc/wolfpack5/03.jpg</a>",
    "<a href=\"http://www.showbizpizza.com/photos/misc/wolfpack5/02.jpg\">http://www.showbizpizza.com/photos/misc/wolfpack5/02.jpg</a>",
    "<a href=\"http://odasan.s48.xrea.com/photo/portpia/port5.html\">http://odasan.s48.xrea.com/photo/portpia/port5.html</a>",
    "<a href=\"https://www.instagram.com/p/Cy6hhsPpwQ1/?igshid=MzRlODBiNWFlZA%3D%3D&img_index=10\">https://www.instagram.com/p/Cy6hhsPpwQ1/?igshid=MzRlODBiNWFlZA%3D%3D&img_index=10</a>",
    "<a href=\"https://www.instagram.com/p/CRAYQBLnvLH/\">https://www.instagram.com/p/CRAYQBLnvLH/</a>",
    "<a href=\"https://youtu.be/GbesEWSt8Jo?t=1573\">https://youtu.be/GbesEWSt8Jo?t=1573</a>",
    "<a href=\"http://www.showbizpizza.com/photos/spp/mo_antioch/index.html\">http://www.showbizpizza.com/photos/spp/mo_antioch/index.html</a>",
    "<a href=\"http://www.showbizpizza.com/info/documents/spp/spp_memos_80.pdf\">http://www.showbizpizza.com/info/documents/spp/spp_memos_80.pdf</a>",
    "<a href=\"http://www.showbizpizza.com/history/index.html\">http://www.showbizpizza.com/history/index.html</a>",
    "<a href=\"https://www.youtube.com/watch?v=GbesEWSt8Jo\">https://www.youtube.com/watch?v=GbesEWSt8Jo</a>",
    "<a href=\"https://www.tapatalk.com/groups/retro_pizza_zone/wolf-pack-5-progress-t3654.html\">https://www.tapatalk.com/groups/retro_pizza_zone/wolf-pack-5-progress-t3654.html</a>"
  ],
  "pageThumbnailFile": "Gaslight_jamboree.avif"
}