{"contributors":295,"articles":1616,"generated":"2026-07-21T11:07:28Z","recent_articles":[{"p":"ym89g2krbam0souy","t":"Christmas '86 Edited Showtape","m":"2026-07-21T11:05:40Z"},{"p":"mnj1nglz2x4qmem0","t":"SPP Movie Magic - R&R I","m":"2026-07-21T11:05:40Z"},{"p":"pok696mp7edktg2h","t":"Elfis (Animatronic)","m":"2026-07-21T11:05:40Z"},{"p":"puc3s4yqc67cxfyi","t":"SPP Summertime - Westerns","m":"2026-07-21T11:05:40Z"},{"p":"ifno5ap2wzm3g3zh","t":"SPP Westerns - Movies - R&R","m":"2026-07-21T11:05:40Z"},{"p":"ckxc31vmt2kukrnn","t":"Christmas Live","m":"2026-07-21T11:05:40Z"},{"p":"46xfsfbn07pfi02w","t":"Willie Rabbit (Animatronic)","m":"2026-07-21T11:05:40Z"},{"p":"a74fo9i5zkr7rzst","t":"SPP Country III - Classics","m":"2026-07-21T11:05:40Z"},{"p":"4qgp1mqssbwy0c6h","t":"SPP Rock-N-Roll Classics","m":"2026-07-21T11:05:40Z"},{"p":"8a5bg2gu1kcoxjqa","t":"Cyberamics Betamax","m":"2026-07-21T11:05:40Z"},{"p":"wr6vevyg20m2a3zb","t":"SPP Working / Summertime","m":"2026-07-18T23:21:25Z"},{"p":"j2qk88ty96x7dsgt","t":"RAE Christmas '81","m":"2026-07-18T23:21:25Z"},{"p":"cmg9be4fw8xvdwh2","t":"Hits / Time Machine","m":"2026-07-18T23:21:25Z"},{"p":"63tuq41126jfd8is","t":"Chuck E. Cheese Twitch","m":"2026-07-18T14:23:12Z"},{"p":"99tg2579j6thegkw","t":"Zapp's Bar & Grill","m":"2026-07-17T18:08:38Z"},{"p":"8my2a9x6vaxm00al","t":"TJ Hartford's Sports Grille","m":"2026-07-17T17:51:25Z"},{"p":"ls7k1890bitfupwx","t":"Dallas, TX (8021 Walnut Hill Lane)","m":"2026-07-17T17:43:17Z"},{"p":"ls7k1890bitfu34f34","t":"Dallas, TX (2905 Forest Lane)","m":"2026-07-17T17:41:50Z"},{"p":"zrgm1ikwc9puw8o9","t":"Cupertino, CA (975 S De Anza Blvd)","m":"2026-07-17T10:05:56Z"},{"p":"99tg25ijnsdkfjnekrjf","t":"Tampa, FL (2363 E. Fowler Ave)","m":"2026-07-17T09:50:31Z"},{"p":"3lfw14eogrw24aun","t":"Reno, NV (651 E Moana Lane)","m":"2026-07-17T07:54:17Z"},{"p":"ns1j38ggyr5slysm","t":"Wolfman Zapp (Cyberamic)","m":"2026-07-17T07:15:48Z"},{"p":"ej8yestjrloryerl","t":"Lewisville, TX (1960 S Stemmons Fwy)","m":"2026-07-17T05:25:51Z"},{"p":"4hkjw4wsm7mit10g","t":"Irving, TX (4560 Regent Blvd, Floor 1)","m":"2026-07-16T08:53:36Z"},{"p":"j5vmsvfy33mp713g","t":"Chuck E. And Friends!","m":"2026-07-16T08:53:28Z"},{"p":"5brkfqf5l9stb767","t":"A Chuck E. Cheese Christmas","m":"2026-07-16T08:25:05Z"},{"p":"9tjtbnjtuv1jxste","t":"Celebration Station","m":"2026-07-16T07:43:59Z"},{"p":"ddjbi44hhmqh4cor","t":"Irving, TX (1707 Market Pl Blvd 200)","m":"2026-07-16T05:00:47Z"},{"p":"zygu8zcgil7u789p","t":"Irving, TX (4441 W Airport Fwy Ste 215)","m":"2026-07-16T04:55:08Z"},{"p":"bds7nm5tkdgnikq4","t":"Intro to Munch's Make Believe Band","m":"2026-07-13T06:58:29Z"}],"recent_photos":[{"p":"m5dpnp4hjouf75r8","t":"5EmsB1zO4LgwKALPvYml.avif","m":"2026-07-21T11:05:40Z"},{"p":"g8ragxyksev3fpes","t":"LVsxrsoL3x3CqD1Js4u3.avif","m":"2026-07-21T11:05:40Z"},{"p":"dhl9shj5bzthl0s2","t":"C533pdjqKwRyPt5Pa_rI.avif","m":"2026-07-21T11:05:40Z"},{"p":"qevcquhm2gehnt23","t":"qevcquhm2gehnt23.avif","m":"2026-07-17T18:07:32Z"},{"p":"ylagzxn5nzfdta4j","t":"ylagzxn5nzfdta4j.avif","m":"2026-07-17T18:06:46Z"},{"p":"0jtasmevhb38lul7","t":"0jtasmevhb38lul7.avif","m":"2026-07-17T18:06:13Z"},{"p":"ggkmf1y7d0keudh1","t":"ggkmf1y7d0keudh1.avif","m":"2026-07-17T18:05:06Z"},{"p":"yv3w71xruntx7rxg","t":"yv3w71xruntx7rxg.avif","m":"2026-07-17T18:05:05Z"},{"p":"9k86fofxoc6vlicu","t":"9k86fofxoc6vlicu.avif","m":"2026-07-17T18:05:04Z"},{"p":"cggr9xgqfujlacra","t":"cggr9xgqfujlacra.avif","m":"2026-07-17T18:05:03Z"},{"p":"3j83srdg0ife5pkg","t":"3j83srdg0ife5pkg.avif","m":"2026-07-17T18:05:03Z"},{"p":"xitk6py574megcbr","t":"xitk6py574megcbr.avif","m":"2026-07-17T18:05:02Z"},{"p":"47avuptmgopa68iu","t":"47avuptmgopa68iu.avif","m":"2026-07-17T18:03:49Z"},{"p":"5n6t0wdtz2hzwl27","t":"5n6t0wdtz2hzwl27.avif","m":"2026-07-17T18:02:53Z"},{"p":"ael86z3idkncgfa5","t":"ael86z3idkncgfa5.avif","m":"2026-07-17T18:02:53Z"},{"p":"ixxz0soewxxhnhdq","t":"ixxz0soewxxhnhdq.avif","m":"2026-07-17T18:02:53Z"},{"p":"89704zdh6dh1chzl","t":"89704zdh6dh1chzl.avif","m":"2026-07-17T18:02:53Z"},{"p":"l5vqd2ovluojjb0n","t":"l5vqd2ovluojjb0n.avif","m":"2026-07-17T18:02:53Z"},{"p":"rchypwhwxbdlwgui","t":"rchypwhwxbdlwgui.avif","m":"2026-07-17T18:02:52Z"},{"p":"2ehla7y64pnislmh","t":"2ehla7y64pnislmh.avif","m":"2026-07-17T18:02:51Z"},{"p":"o34b89pupwh3e4lu","t":"o34b89pupwh3e4lu.avif","m":"2026-07-17T18:02:51Z"},{"p":"anphjazxftoby46u","t":"anphjazxftoby46u.avif","m":"2026-07-17T18:01:52Z"},{"p":"a9u2vl48f3wetdcr","t":"a9u2vl48f3wetdcr.avif","m":"2026-07-17T18:01:52Z"},{"p":"zs6w31052l5sh283","t":"zs6w31052l5sh283.avif","m":"2026-07-17T18:01:52Z"},{"p":"e0vwsymys9wfohnw","t":"e0vwsymys9wfohnw.avif","m":"2026-07-17T18:01:52Z"},{"p":"185k4grq9myakjez","t":"185k4grq9myakjez.avif","m":"2026-07-17T18:01:51Z"},{"p":"5lsmhf9kfvd1uoxk","t":"5lsmhf9kfvd1uoxk.avif","m":"2026-07-17T18:01:51Z"},{"p":"ni9aflwr3bnkrwc2","t":"ni9aflwr3bnkrwc2.avif","m":"2026-07-17T18:01:50Z"},{"p":"4jb5vqzj8phzsrl6","t":"4jb5vqzj8phzsrl6.avif","m":"2026-07-16T08:50:27Z"},{"p":"hlospqqmnmk7xh8c","t":"hlospqqmnmk7xh8c.avif","m":"2026-07-16T08:50:15Z"}],"recent_videos":[{"p":"dttvb5wfo4wkthrc","t":"","m":"2026-04-16T08:46:52Z"},{"p":"tz9dkfe0x4ym8joh","t":"https://youtu.be/opeTLlnISNY?si=27XSLSfhrK_yoLjS","m":"2026-03-24T03:51:52Z"},{"p":"bysltpndnse61s5p","t":"https://youtu.be/6L7fgPGzQo8?si=MohKtkIawi-yHPHu","m":"2026-03-23T08:30:09Z"},{"p":"hd222sht144iq83m","t":"https://youtu.be/NHCZPsjjopY?si=hehyUq45Nw-DUeRT","m":"2026-03-23T08:30:09Z"},{"p":"tmvwgadm3ai0t0n7","t":"https://youtu.be/W3zsvrQpXrQ","m":"2026-03-23T08:29:03Z"},{"p":"y1i736ddu4vfmhtt","t":"https://youtu.be/L5s_o8j9-Fk","m":"2026-03-23T08:29:03Z"},{"p":"7ljusinvob1zgelc","t":"https://youtu.be/ENHUFL4c74g","m":"2026-03-23T08:29:03Z"},{"p":"q5pbp8y4mr8scjod","t":"https://youtu.be/I7AGe1Uu3g8","m":"2026-03-23T08:29:03Z"},{"p":"y856avnu71842ygi","t":"https://youtu.be/RJ9867iHsKs","m":"2026-03-23T08:29:03Z"},{"p":"3tr0mankoh8f99is","t":"https://youtu.be/q85IUzIMGFA","m":"2026-03-23T08:29:03Z"},{"p":"3w4t0xq317u3aut6","t":"https://youtu.be/MRtZbz7znqo","m":"2026-03-23T08:29:03Z"},{"p":"bymzona60wzf8kzo","t":"https://youtu.be/T2VmsTWWi-w","m":"2026-03-23T08:29:03Z"},{"p":"5y3jlrcjqc0zmm3c","t":"https://youtu.be/8b6y6YmBfmA","m":"2026-03-23T08:29:03Z"},{"p":"wrcwq253but8gopc","t":"https://youtu.be/Iutumc36J9U","m":"2026-03-23T08:29:03Z"},{"p":"rdv0oj5iu2rnotsv","t":"https://youtu.be/MnN1YhB0KAk","m":"2026-03-23T08:29:03Z"},{"p":"3ksd4gfbqf0ojhb6","t":"https://youtu.be/EtosT11UTvI","m":"2026-03-23T08:29:03Z"},{"p":"mfou6j6js6usrmti","t":"https://youtu.be/9vC2DhBEaPM","m":"2026-03-23T08:29:03Z"},{"p":"pns2b22qgyf5fqz4","t":"https://youtu.be/uACEAWasRCk","m":"2026-03-23T08:29:03Z"},{"p":"5g4bpjy4ypbiueir","t":"https://youtu.be/Zru1DUVYY7U","m":"2026-03-23T08:29:03Z"},{"p":"7f27pnboo8elnbwy","t":"(Unofficial) FNaF Night 2 Gameplay","m":"2026-03-18T02:33:06Z"},{"p":"wg91yq67wuxt7e0l","t":"(Unofficial) FNaF Night 1 Gameplay","m":"2026-03-18T02:33:06Z"},{"p":"my2szvqfdtbp9dup","t":"(Unofficial) FNaF Night 4 Gameplay","m":"2026-03-18T02:33:06Z"},{"p":"jly2qcguhhsmkjtl","t":"(Unofficial) FNaF Night 5 Gameplay","m":"2026-03-18T02:33:06Z"},{"p":"f069uvamf8n26mk6","t":"(Unofficial) FNaF Night 3 Gameplay","m":"2026-03-18T02:33:05Z"},{"p":"6d8014kltcquk6fn","t":"(Unofficial) FNaF Night 6 Gameplay","m":"2026-03-18T02:33:05Z"},{"p":"3pwjqee3j6cqb929","t":"(Unofficial) FNaF Custom Night 20/20/20/20 Gameplay","m":"2026-03-18T02:33:05Z"},{"p":"id4j8980ovhlgoyx","t":"Scott Cawthon FNaF Gameplay","m":"2026-03-18T02:33:05Z"},{"p":"vw717ic36qxvfjlj","t":"Five Nights at Freddy's Official Trailer","m":"2026-03-18T02:33:05Z"},{"p":"eyv4412hie6w5emd","t":"https://youtu.be/lm5Yiegq3bs","m":"2026-03-15T07:46:57Z"},{"p":"a8duig2ziphvg9yd","t":"https://youtu.be/BJ4d0N8RHis","m":"2026-03-15T07:46:57Z"}]}