{
  "title": "Bridgewater, NJ (600 Promenade Blvd)",
  "storeNumber": "",
  "startDate": "2000-02-07",
  "endDate": "2024-04-07",
  
  "remodels": [
    {
      "n": "Low Volume Store Initiative",
      "s": "2024-00-00"
    }
  ],
  "stages": [
    {
      "n": "Studio C Alpha",
      "s": "2000-02-07",
      "e": "2024-04-07"
    }
  ],
  "franchisees": [],
  "attractions": [],
  "sqft": "",
  "latitudeLongitude": [
    "40.56585242",
    "-74.55869008"
  ],
  "citations": [],
  "contributors": [],
  "downloadLinks": [],
  "pageThumbnailFile": "mItk1hqHgHtZR2J8pOK3.avif",
  "type": "Locations",
  "tags": [
    "Chuck E. Cheese's"
  ]
}