{
  "title": "Cupertino, CA (19805 Stevens Creek Blvd)",
  "storeNumber": "",
  "startDate": "2006-11-15",
  "endDate": "",
  
  "remodels": [],
  "stages": [
    {
      "n": "Studio C Beta",
      "s": "2006-11-15",
      "e": "0000-00-00"
    },
    {
      "n": "Chuck E. Live Stage (Dance Floor)",
      "s": "0000-00-00"
    }
  ],
  "franchisees": [],
  "attractions": [],
  "sqft": "",
  "latitudeLongitude": [
    "37.3229469",
    "-122.0036874"
  ],
  "citations": [],
  "contributors": [],
  "downloadLinks": [],
  "pageThumbnailFile": "",
  "type": "Locations",
  "tags": [
    "Chuck E. Cheese's"
  ]
}