{"users": [{"id": 1, "username": "The-64th-Gamer", "name": "The 64th Gamer", "avatar_template": "/user_avatar/forum.cheeseepedia.org/the-64th-gamer/{size}/149_2.png", "primary_group_name": "BankruptcyBelievers", "flair_name": "BankruptcyBelievers", "flair_url": "building-columns", "flair_bg_color": "352240", "flair_color": "FFFFFF", "flair_group_id": 41, "admin": true, "moderator": true, "trust_level": 2}, {"id": 26, "username": "randomguyfan22-maker", "name": "Randomguyfan22 Maker", "avatar_template": "/user_avatar/forum.cheeseepedia.org/randomguyfan22-maker/{size}/1088_2.png", "primary_group_name": "BankruptcyBelievers", "flair_name": "BankruptcyBelievers", "flair_url": "building-columns", "flair_bg_color": "352240", "flair_color": "FFFFFF", "flair_group_id": 41, "trust_level": 1}, {"id": 17, "username": "PizzaEntertainment", "name": "Pizza Entertainment Fan", "avatar_template": "/user_avatar/forum.cheeseepedia.org/pizzaentertainment/{size}/265_2.png", "primary_group_name": "BankruptcyBelievers", "flair_name": "BankruptcyBelievers", "flair_url": "building-columns", "flair_bg_color": "352240", "flair_color": "FFFFFF", "flair_group_id": 41, "trust_level": 2}, {"id": 65, "username": "CECR995", "name": "", "avatar_template": "/user_avatar/forum.cheeseepedia.org/cecr995/{size}/1181_2.png", "primary_group_name": "BankruptcyBelievers", "flair_name": "BankruptcyBelievers", "flair_url": "building-columns", "flair_bg_color": "352240", "flair_color": "FFFFFF", "flair_group_id": 41, "trust_level": 1}, {"id": 9, "username": "CyberSnout", "name": "Cyber Snout", "avatar_template": "/user_avatar/forum.cheeseepedia.org/cybersnout/{size}/159_2.png", "primary_group_name": "BankruptcyBelievers", "flair_name": "BankruptcyBelievers", "flair_url": "building-columns", "flair_bg_color": "352240", "flair_color": "FFFFFF", "flair_group_id": 41, "trust_level": 2}, {"id": 25, "username": "crunchybeans", "name": "stel/bug/crunchy (they/them)", "avatar_template": "/user_avatar/forum.cheeseepedia.org/crunchybeans/{size}/491_2.png", "trust_level": 2}, {"id": 61, "username": "cmsentance-byte", "name": "Cmsentance Byte", "avatar_template": "/user_avatar/forum.cheeseepedia.org/cmsentance-byte/{size}/908_2.png", "trust_level": 1}, {"id": 76, "username": "ToadEatSock", "name": null, "avatar_template": "/letter_avatar_proxy/v4/letter/t/3d9bf3/{size}.png", "trust_level": 0}, {"id": 19, "username": "AccountHalf", "name": "Account Half", "avatar_template": "/user_avatar/forum.cheeseepedia.org/accounthalf/{size}/308_2.png", "trust_level": 1}, {"id": 16, "username": "FileFickle", "name": "", "avatar_template": "/user_avatar/forum.cheeseepedia.org/filefickle/{size}/269_2.png", "trust_level": 1}, {"id": 27, "username": "GallaRM", "name": "Galla", "avatar_template": "/user_avatar/forum.cheeseepedia.org/gallarm/{size}/382_2.png", "primary_group_name": "BankruptcyBelievers", "flair_name": "BankruptcyBelievers", "flair_url": "building-columns", "flair_bg_color": "352240", "flair_color": "FFFFFF", "flair_group_id": 41, "trust_level": 2}, {"id": 12, "username": "Ceclife13", "name": "", "avatar_template": "/user_avatar/forum.cheeseepedia.org/ceclife13/{size}/201_2.png", "primary_group_name": "BankruptcyBelievers", "flair_name": "BankruptcyBelievers", "flair_url": "building-columns", "flair_bg_color": "352240", "flair_color": "FFFFFF", "flair_group_id": 41, "moderator": true, "trust_level": 1}, {"id": 7, "username": "JuanMorales", "name": "Juan Pablo Morales", "avatar_template": "/user_avatar/forum.cheeseepedia.org/juanmorales/{size}/160_2.png", "flair_name": "InternationalFan", "flair_url": "earth-europe", "flair_bg_color": "44BD53", "flair_color": "FFFF", "flair_group_id": 49, "trust_level": 2}], "primary_groups": [{"id": 41, "name": "BankruptcyBelievers"}], "flair_groups": [{"id": 41, "name": "BankruptcyBelievers", "flair_url": "building-columns", "flair_bg_color": "352240", "flair_color": "FFFFFF"}, {"id": 49, "name": "InternationalFan", "flair_url": "earth-europe", "flair_bg_color": "44BD53", "flair_color": "FFFF"}], "topic_list": {"can_create_topic": false, "more_topics_url": "/c/news/5/l/latest?order=created&page=1", "per_page": 30, "top_tags": ["chuck-e-cheese", "lost-media", "bankruptcy-believers", "cheese-e-pedia", "pizza-time-theatre", "cec-animated-series", "adventure-world", "rock-afire-explosion", "showbiz-pizza-place", "chucks-arcade", "fnaf", "creative-engineering", "merchandise", "topic-of-the-month", "aam", "animated-fx", "legacy-location", "showbiz-pizza-time", "simulator"], "topics": [{"fancy_title": "Topic of the Month: Arcades &amp; Attractions", "id": 237, "title": "Topic of the Month: Arcades & Attractions", "slug": "topic-of-the-month-arcades-attractions", "posts_count": 1, "reply_count": 0, "highest_post_number": 1, "image_url": "https://forum.cheeseepedia.org/uploads/default/original/2X/7/7ecbdcf6b1ed0d6829e7a63255dca86a3a469c79.jpeg", "created_at": "2026-02-01T21:31:37.770Z", "last_posted_at": "2026-02-01T21:31:37.929Z", "bumped": true, "bumped_at": "2026-02-01T21:31:37.929Z", "archetype": "regular", "unseen": false, "pinned": false, "unpinned": null, "visible": true, "closed": false, "archived": false, "bookmarked": null, "liked": null, "thumbnails": [{"max_width": null, "max_height": null, "width": 490, "height": 489, "url": "https://forum.cheeseepedia.org/uploads/default/original/2X/7/7ecbdcf6b1ed0d6829e7a63255dca86a3a469c79.jpeg"}, {"max_width": 400, "max_height": 400, "width": 400, "height": 399, "url": "https://forum.cheeseepedia.org/uploads/default/optimized/2X/7/7ecbdcf6b1ed0d6829e7a63255dca86a3a469c79_2_400x399.jpeg"}, {"max_width": 300, "max_height": 300, "width": 300, "height": 299, "url": "https://forum.cheeseepedia.org/uploads/default/optimized/2X/7/7ecbdcf6b1ed0d6829e7a63255dca86a3a469c79_2_300x299.jpeg"}, {"max_width": 200, "max_height": 200, "width": 200, "height": 199, "url": "https://forum.cheeseepedia.org/uploads/default/optimized/2X/7/7ecbdcf6b1ed0d6829e7a63255dca86a3a469c79_2_200x199.jpeg"}], "tags": ["topic-of-the-month"], "tags_descriptions": {}, "views": 2, "like_count": 0, "has_summary": false, "last_poster_username": "The-64th-Gamer", "category_id": 5, "op_like_count": 0, "pinned_globally": false, "featured_link": null, "has_accepted_answer": false, "can_vote": false, "posters": [{"extras": "latest single", "description": "Original Poster, Most Recent Poster", "user_id": 1, "primary_group_id": 41, "flair_group_id": 41}]}, {"fancy_title": "CEP Moves Hosts", "id": 235, "title": "CEP Moves Hosts", "slug": "cep-moves-hosts", "posts_count": 1, "reply_count": 0, "highest_post_number": 1, "image_url": "https://forum.cheeseepedia.org/uploads/default/original/2X/5/564d10ff25fa3a924cbbe140004298b31c612809.gif", "created_at": "2026-02-01T07:29:29.190Z", "last_posted_at": "2026-02-01T07:29:29.390Z", "bumped": true, "bumped_at": "2026-02-01T07:29:29.390Z", "archetype": "regular", "unseen": false, "pinned": false, "unpinned": null, "visible": true, "closed": false, "archived": false, "bookmarked": null, "liked": null, "thumbnails": [{"max_width": null, "max_height": null, "width": 480, "height": 360, "url": "https://forum.cheeseepedia.org/uploads/default/original/2X/5/564d10ff25fa3a924cbbe140004298b31c612809.gif"}, {"max_width": 400, "max_height": 400, "width": 400, "height": 300, "url": "https://forum.cheeseepedia.org/uploads/default/optimized/2X/5/564d10ff25fa3a924cbbe140004298b31c612809_2_400x300.gif"}, {"max_width": 300, "max_height": 300, "width": 300, "height": 225, "url": "https://forum.cheeseepedia.org/uploads/default/optimized/2X/5/564d10ff25fa3a924cbbe140004298b31c612809_2_300x225.gif"}, {"max_width": 200, "max_height": 200, "width": 200, "height": 150, "url": "https://forum.cheeseepedia.org/uploads/default/optimized/2X/5/564d10ff25fa3a924cbbe140004298b31c612809_2_200x150.gif"}], "tags": ["cheese-e-pedia"], "tags_descriptions": {}, "views": 12, "like_count": 0, "has_summary": false, "last_poster_username": "The-64th-Gamer", "category_id": 5, "op_like_count": 0, "pinned_globally": false, "featured_link": null, "has_accepted_answer": false, "can_vote": false, "posters": [{"extras": "latest single", "description": "Original Poster, Most Recent Poster", "user_id": 1, "primary_group_id": 41, "flair_group_id": 41}]}, {"fancy_title": "New &lsquo;Super Fun&rsquo; Playground at CEC&rsquo;s?", "id": 228, "title": "New 'Super Fun' Playground at CEC's?", "slug": "new-super-fun-playground-at-cecs", "posts_count": 1, "reply_count": 0, "highest_post_number": 1, "image_url": "https://forum.cheeseepedia.org/uploads/default/original/2X/3/35a5a33705f21827461df7c4856a9103d42d7084.jpeg", "created_at": "2026-01-27T23:21:35.553Z", "last_posted_at": "2026-01-27T23:21:35.779Z", "bumped": true, "bumped_at": "2026-01-27T23:21:35.779Z", "archetype": "regular", "unseen": false, "pinned": false, "unpinned": null, "visible": true, "closed": false, "archived": false, "bookmarked": null, "liked": null, "thumbnails": [{"max_width": null, "max_height": null, "width": 360, "height": 270, "url": "https://forum.cheeseepedia.org/uploads/default/original/2X/3/35a5a33705f21827461df7c4856a9103d42d7084.jpeg"}, {"max_width": 300, "max_height": 300, "width": 300, "height": 225, "url": "https://forum.cheeseepedia.org/uploads/default/optimized/2X/3/35a5a33705f21827461df7c4856a9103d42d7084_2_300x225.jpeg"}, {"max_width": 200, "max_height": 200, "width": 200, "height": 150, "url": "https://forum.cheeseepedia.org/uploads/default/optimized/2X/3/35a5a33705f21827461df7c4856a9103d42d7084_2_200x150.jpeg"}], "tags": ["chuck-e-cheese", "bankruptcy-believers"], "tags_descriptions": {}, "views": 163, "like_count": 1, "has_summary": false, "last_poster_username": "The-64th-Gamer", "category_id": 5, "op_like_count": 1, "pinned_globally": false, "featured_link": null, "has_accepted_answer": false, "can_vote": false, "posters": [{"extras": "latest single", "description": "Original Poster, Most Recent Poster", "user_id": 1, "primary_group_id": 41, "flair_group_id": 41}]}, {"fancy_title": "CEC Location Planned for 2028 Mall Plaza Tr\u00e9bol Expansion", "id": 227, "title": "CEC Location Planned for 2028 Mall Plaza Tr\u00e9bol Expansion", "slug": "cec-location-planned-for-2028-mall-plaza-trebol-expansion", "posts_count": 2, "reply_count": 0, "highest_post_number": 2, "image_url": "https://forum.cheeseepedia.org/uploads/default/original/2X/c/c5ce70db08c086bf8acb393fadfa0332e11feb34.jpeg", "created_at": "2026-01-27T22:22:20.001Z", "last_posted_at": "2026-01-28T01:43:23.554Z", "bumped": true, "bumped_at": "2026-01-28T01:43:23.554Z", "archetype": "regular", "unseen": false, "pinned": false, "unpinned": null, "visible": true, "closed": false, "archived": false, "bookmarked": null, "liked": null, "thumbnails": [{"max_width": null, "max_height": null, "width": 789, "height": 482, "url": "https://forum.cheeseepedia.org/uploads/default/original/2X/c/c5ce70db08c086bf8acb393fadfa0332e11feb34.jpeg"}, {"max_width": 600, "max_height": 600, "width": 600, "height": 366, "url": "https://forum.cheeseepedia.org/uploads/default/optimized/2X/c/c5ce70db08c086bf8acb393fadfa0332e11feb34_2_600x366.jpeg"}, {"max_width": 400, "max_height": 400, "width": 400, "height": 244, "url": "https://forum.cheeseepedia.org/uploads/default/optimized/2X/c/c5ce70db08c086bf8acb393fadfa0332e11feb34_2_400x244.jpeg"}, {"max_width": 300, "max_height": 300, "width": 300, "height": 183, "url": "https://forum.cheeseepedia.org/uploads/default/optimized/2X/c/c5ce70db08c086bf8acb393fadfa0332e11feb34_2_300x183.jpeg"}, {"max_width": 200, "max_height": 200, "width": 200, "height": 122, "url": "https://forum.cheeseepedia.org/uploads/default/optimized/2X/c/c5ce70db08c086bf8acb393fadfa0332e11feb34_2_200x122.jpeg"}], "tags": ["chuck-e-cheese"], "tags_descriptions": {}, "views": 159, "like_count": 2, "has_summary": false, "last_poster_username": "randomguyfan22-maker", "category_id": 5, "op_like_count": 1, "pinned_globally": false, "featured_link": null, "has_accepted_answer": false, "can_vote": false, "posters": [{"extras": null, "description": "Original Poster", "user_id": 1, "primary_group_id": 41, "flair_group_id": 41}, {"extras": "latest", "description": "Most Recent Poster", "user_id": 26, "primary_group_id": 41, "flair_group_id": 41}]}, {"fancy_title": "CEP Media Player In Testing", "id": 225, "title": "CEP Media Player In Testing", "slug": "cep-media-player-in-testing", "posts_count": 1, "reply_count": 0, "highest_post_number": 1, "image_url": "https://forum.cheeseepedia.org/uploads/default/optimized/2X/7/750d4db56462338f5e71758ec33c0f4620bfc3ae_2_1024x702.jpeg", "created_at": "2026-01-25T12:01:12.751Z", "last_posted_at": "2026-01-25T12:01:12.908Z", "bumped": true, "bumped_at": "2026-01-25T12:01:12.908Z", "archetype": "regular", "unseen": false, "pinned": false, "unpinned": null, "visible": true, "closed": false, "archived": false, "bookmarked": null, "liked": null, "thumbnails": [{"max_width": null, "max_height": null, "width": 1390, "height": 953, "url": "https://forum.cheeseepedia.org/uploads/default/original/2X/7/750d4db56462338f5e71758ec33c0f4620bfc3ae.jpeg"}, {"max_width": 1024, "max_height": 1024, "width": 1024, "height": 702, "url": "https://forum.cheeseepedia.org/uploads/default/optimized/2X/7/750d4db56462338f5e71758ec33c0f4620bfc3ae_2_1024x702.jpeg"}, {"max_width": 800, "max_height": 800, "width": 800, "height": 548, "url": "https://forum.cheeseepedia.org/uploads/default/optimized/2X/7/750d4db56462338f5e71758ec33c0f4620bfc3ae_2_800x548.jpeg"}, {"max_width": 600, "max_height": 600, "width": 600, "height": 411, "url": "https://forum.cheeseepedia.org/uploads/default/optimized/2X/7/750d4db56462338f5e71758ec33c0f4620bfc3ae_2_600x411.jpeg"}, {"max_width": 400, "max_height": 400, "width": 400, "height": 274, "url": "https://forum.cheeseepedia.org/uploads/default/optimized/2X/7/750d4db56462338f5e71758ec33c0f4620bfc3ae_2_400x274.jpeg"}, {"max_width": 300, "max_height": 300, "width": 300, "height": 205, "url": "https://forum.cheeseepedia.org/uploads/default/optimized/2X/7/750d4db56462338f5e71758ec33c0f4620bfc3ae_2_300x205.jpeg"}, {"max_width": 200, "max_height": 200, "width": 200, "height": 137, "url": "https://forum.cheeseepedia.org/uploads/default/optimized/2X/7/750d4db56462338f5e71758ec33c0f4620bfc3ae_2_200x137.jpeg"}], "tags": ["cheese-e-pedia"], "tags_descriptions": {}, "views": 134, "like_count": 2, "has_summary": false, "last_poster_username": "The-64th-Gamer", "category_id": 5, "op_like_count": 2, "pinned_globally": false, "featured_link": null, "has_accepted_answer": false, "can_vote": false, "posters": [{"extras": "latest single", "description": "Original Poster, Most Recent Poster", "user_id": 1, "primary_group_id": 41, "flair_group_id": 41}]}, {"fancy_title": "Another Unnanounced CEC Arcade Uncovered", "id": 222, "title": "Another Unnanounced CEC Arcade Uncovered", "slug": "another-unnanounced-cec-arcade-uncovered", "posts_count": 4, "reply_count": 0, "highest_post_number": 4, "image_url": "https://forum.cheeseepedia.org/uploads/default/optimized/2X/e/e821dc947037a49539bf7afeed5d27018ff4e69f_2_1024x576.jpeg", "created_at": "2026-01-22T04:25:59.796Z", "last_posted_at": "2026-01-29T17:39:42.481Z", "bumped": true, "bumped_at": "2026-01-29T17:39:42.481Z", "archetype": "regular", "unseen": false, "pinned": false, "unpinned": null, "visible": true, "closed": false, "archived": false, "bookmarked": null, "liked": null, "thumbnails": [{"max_width": null, "max_height": null, "width": 1280, "height": 720, "url": "https://forum.cheeseepedia.org/uploads/default/original/2X/e/e821dc947037a49539bf7afeed5d27018ff4e69f.jpeg"}, {"max_width": 1024, "max_height": 1024, "width": 1024, "height": 576, "url": "https://forum.cheeseepedia.org/uploads/default/optimized/2X/e/e821dc947037a49539bf7afeed5d27018ff4e69f_2_1024x576.jpeg"}, {"max_width": 800, "max_height": 800, "width": 800, "height": 450, "url": "https://forum.cheeseepedia.org/uploads/default/optimized/2X/e/e821dc947037a49539bf7afeed5d27018ff4e69f_2_800x450.jpeg"}, {"max_width": 600, "max_height": 600, "width": 600, "height": 337, "url": "https://forum.cheeseepedia.org/uploads/default/optimized/2X/e/e821dc947037a49539bf7afeed5d27018ff4e69f_2_600x337.jpeg"}, {"max_width": 400, "max_height": 400, "width": 400, "height": 225, "url": "https://forum.cheeseepedia.org/uploads/default/optimized/2X/e/e821dc947037a49539bf7afeed5d27018ff4e69f_2_400x225.jpeg"}, {"max_width": 300, "max_height": 300, "width": 300, "height": 168, "url": "https://forum.cheeseepedia.org/uploads/default/optimized/2X/e/e821dc947037a49539bf7afeed5d27018ff4e69f_2_300x168.jpeg"}, {"max_width": 200, "max_height": 200, "width": 200, "height": 112, "url": "https://forum.cheeseepedia.org/uploads/default/optimized/2X/e/e821dc947037a49539bf7afeed5d27018ff4e69f_2_200x112.jpeg"}], "tags": ["chuck-e-cheese", "chucks-arcade"], "tags_descriptions": {}, "views": 201, "like_count": 1, "has_summary": false, "last_poster_username": "CECR995", "category_id": 5, "op_like_count": 1, "pinned_globally": false, "featured_link": null, "has_accepted_answer": false, "can_vote": false, "posters": [{"extras": null, "description": "Original Poster", "user_id": 1, "primary_group_id": 41, "flair_group_id": 41}, {"extras": null, "description": "Frequent Poster", "user_id": 17, "primary_group_id": 41, "flair_group_id": 41}, {"extras": "latest", "description": "Most Recent Poster", "user_id": 65, "primary_group_id": 41, "flair_group_id": 41}]}, {"fancy_title": "New Hong Kong Pizza Time Theatre Discovered", "id": 213, "title": "New Hong Kong Pizza Time Theatre Discovered", "slug": "new-hong-kong-pizza-time-theatre-discovered", "posts_count": 4, "reply_count": 2, "highest_post_number": 4, "image_url": "https://forum.cheeseepedia.org/uploads/default/original/2X/6/6c17e8a90cacad08fc1669985e11ab08a84adf0e.jpeg", "created_at": "2026-01-18T22:26:03.347Z", "last_posted_at": "2026-01-18T22:43:32.002Z", "bumped": true, "bumped_at": "2026-01-18T22:43:32.002Z", "archetype": "regular", "unseen": false, "pinned": false, "unpinned": null, "visible": true, "closed": false, "archived": false, "bookmarked": null, "liked": null, "thumbnails": [{"max_width": null, "max_height": null, "width": 485, "height": 353, "url": "https://forum.cheeseepedia.org/uploads/default/original/2X/6/6c17e8a90cacad08fc1669985e11ab08a84adf0e.jpeg"}, {"max_width": 400, "max_height": 400, "width": 400, "height": 291, "url": "https://forum.cheeseepedia.org/uploads/default/optimized/2X/6/6c17e8a90cacad08fc1669985e11ab08a84adf0e_2_400x291.jpeg"}, {"max_width": 300, "max_height": 300, "width": 300, "height": 218, "url": "https://forum.cheeseepedia.org/uploads/default/optimized/2X/6/6c17e8a90cacad08fc1669985e11ab08a84adf0e_2_300x218.jpeg"}, {"max_width": 200, "max_height": 200, "width": 200, "height": 145, "url": "https://forum.cheeseepedia.org/uploads/default/optimized/2X/6/6c17e8a90cacad08fc1669985e11ab08a84adf0e_2_200x145.jpeg"}], "tags": ["pizza-time-theatre", "lost-media"], "tags_descriptions": {}, "views": 294, "like_count": 2, "has_summary": false, "last_poster_username": "PizzaEntertainment", "category_id": 5, "op_like_count": 1, "pinned_globally": false, "featured_link": null, "has_accepted_answer": false, "can_vote": false, "posters": [{"extras": null, "description": "Original Poster", "user_id": 1, "primary_group_id": 41, "flair_group_id": 41}, {"extras": null, "description": "Frequent Poster", "user_id": 9, "primary_group_id": 41, "flair_group_id": 41}, {"extras": "latest", "description": "Most Recent Poster", "user_id": 17, "primary_group_id": 41, "flair_group_id": 41}]}, {"fancy_title": "Duncan Brannan Does 40 Minute CEC Q/A", "id": 212, "title": "Duncan Brannan Does 40 Minute CEC Q/A", "slug": "duncan-brannan-does-40-minute-cec-q-a", "posts_count": 1, "reply_count": 0, "highest_post_number": 1, "image_url": "https://forum.cheeseepedia.org/uploads/default/optimized/2X/a/ad76ddeea48f527e61a4f07acae9da6d2c58b19b_2_1024x576.jpeg", "created_at": "2026-01-18T07:35:25.708Z", "last_posted_at": "2026-01-18T07:35:25.878Z", "bumped": true, "bumped_at": "2026-01-18T07:35:25.878Z", "archetype": "regular", "unseen": false, "pinned": false, "unpinned": null, "visible": true, "closed": false, "archived": false, "bookmarked": null, "liked": null, "thumbnails": [{"max_width": null, "max_height": null, "width": 1280, "height": 720, "url": "https://forum.cheeseepedia.org/uploads/default/original/2X/a/ad76ddeea48f527e61a4f07acae9da6d2c58b19b.jpeg"}, {"max_width": 1024, "max_height": 1024, "width": 1024, "height": 576, "url": "https://forum.cheeseepedia.org/uploads/default/optimized/2X/a/ad76ddeea48f527e61a4f07acae9da6d2c58b19b_2_1024x576.jpeg"}, {"max_width": 800, "max_height": 800, "width": 800, "height": 450, "url": "https://forum.cheeseepedia.org/uploads/default/optimized/2X/a/ad76ddeea48f527e61a4f07acae9da6d2c58b19b_2_800x450.jpeg"}, {"max_width": 600, "max_height": 600, "width": 600, "height": 337, "url": "https://forum.cheeseepedia.org/uploads/default/optimized/2X/a/ad76ddeea48f527e61a4f07acae9da6d2c58b19b_2_600x337.jpeg"}, {"max_width": 400, "max_height": 400, "width": 400, "height": 225, "url": "https://forum.cheeseepedia.org/uploads/default/optimized/2X/a/ad76ddeea48f527e61a4f07acae9da6d2c58b19b_2_400x225.jpeg"}, {"max_width": 300, "max_height": 300, "width": 300, "height": 168, "url": "https://forum.cheeseepedia.org/uploads/default/optimized/2X/a/ad76ddeea48f527e61a4f07acae9da6d2c58b19b_2_300x168.jpeg"}, {"max_width": 200, "max_height": 200, "width": 200, "height": 112, "url": "https://forum.cheeseepedia.org/uploads/default/optimized/2X/a/ad76ddeea48f527e61a4f07acae9da6d2c58b19b_2_200x112.jpeg"}], "tags": ["chuck-e-cheese"], "tags_descriptions": {}, "views": 149, "like_count": 0, "has_summary": false, "last_poster_username": "The-64th-Gamer", "category_id": 5, "op_like_count": 0, "pinned_globally": false, "featured_link": null, "has_accepted_answer": false, "can_vote": false, "posters": [{"extras": "latest single", "description": "Original Poster, Most Recent Poster", "user_id": 1, "primary_group_id": 41, "flair_group_id": 41}]}, {"fancy_title": "Jay Spears Steps Down as Chief Information Officer", "id": 211, "title": "Jay Spears Steps Down as Chief Information Officer", "slug": "jay-spears-steps-down-as-chief-information-officer", "posts_count": 1, "reply_count": 0, "highest_post_number": 1, "image_url": "https://forum.cheeseepedia.org/uploads/default/original/2X/3/329fee3309f236b3916d47cb5643405ca9d157bb.jpeg", "created_at": "2026-01-17T22:18:49.985Z", "last_posted_at": "2026-01-17T22:18:50.168Z", "bumped": true, "bumped_at": "2026-01-17T22:18:50.168Z", "archetype": "regular", "unseen": false, "pinned": false, "unpinned": null, "visible": true, "closed": false, "archived": false, "bookmarked": null, "liked": null, "thumbnails": [{"max_width": null, "max_height": null, "width": 916, "height": 552, "url": "https://forum.cheeseepedia.org/uploads/default/original/2X/3/329fee3309f236b3916d47cb5643405ca9d157bb.jpeg"}, {"max_width": 800, "max_height": 800, "width": 800, "height": 482, "url": "https://forum.cheeseepedia.org/uploads/default/optimized/2X/3/329fee3309f236b3916d47cb5643405ca9d157bb_2_800x482.jpeg"}, {"max_width": 600, "max_height": 600, "width": 600, "height": 361, "url": "https://forum.cheeseepedia.org/uploads/default/optimized/2X/3/329fee3309f236b3916d47cb5643405ca9d157bb_2_600x361.jpeg"}, {"max_width": 400, "max_height": 400, "width": 400, "height": 241, "url": "https://forum.cheeseepedia.org/uploads/default/optimized/2X/3/329fee3309f236b3916d47cb5643405ca9d157bb_2_400x241.jpeg"}, {"max_width": 300, "max_height": 300, "width": 300, "height": 180, "url": "https://forum.cheeseepedia.org/uploads/default/optimized/2X/3/329fee3309f236b3916d47cb5643405ca9d157bb_2_300x180.jpeg"}, {"max_width": 200, "max_height": 200, "width": 200, "height": 120, "url": "https://forum.cheeseepedia.org/uploads/default/optimized/2X/3/329fee3309f236b3916d47cb5643405ca9d157bb_2_200x120.jpeg"}], "tags": ["chuck-e-cheese", "bankruptcy-believers"], "tags_descriptions": {}, "views": 192, "like_count": 1, "has_summary": false, "last_poster_username": "The-64th-Gamer", "category_id": 5, "op_like_count": 1, "pinned_globally": false, "featured_link": null, "has_accepted_answer": false, "can_vote": false, "posters": [{"extras": "latest single", "description": "Original Poster, Most Recent Poster", "user_id": 1, "primary_group_id": 41, "flair_group_id": 41}]}, {"fancy_title": "CEC: What to Expect for 2026", "id": 206, "title": "CEC: What to Expect for 2026", "slug": "cec-what-to-expect-for-2026", "posts_count": 5, "reply_count": 3, "highest_post_number": 5, "image_url": "https://forum.cheeseepedia.org/uploads/default/optimized/2X/5/5e4cbf41cc77a3392df25fdea3703cc35011d456_2_1024x576.jpeg", "created_at": "2026-01-16T03:20:52.036Z", "last_posted_at": "2026-01-17T23:01:26.974Z", "bumped": true, "bumped_at": "2026-01-17T23:01:26.974Z", "archetype": "regular", "unseen": false, "pinned": false, "unpinned": null, "visible": true, "closed": false, "archived": false, "bookmarked": null, "liked": null, "thumbnails": [{"max_width": null, "max_height": null, "width": 1280, "height": 720, "url": "https://forum.cheeseepedia.org/uploads/default/original/2X/5/5e4cbf41cc77a3392df25fdea3703cc35011d456.jpeg"}, {"max_width": 1024, "max_height": 1024, "width": 1024, "height": 576, "url": "https://forum.cheeseepedia.org/uploads/default/optimized/2X/5/5e4cbf41cc77a3392df25fdea3703cc35011d456_2_1024x576.jpeg"}, {"max_width": 800, "max_height": 800, "width": 800, "height": 450, "url": "https://forum.cheeseepedia.org/uploads/default/optimized/2X/5/5e4cbf41cc77a3392df25fdea3703cc35011d456_2_800x450.jpeg"}, {"max_width": 600, "max_height": 600, "width": 600, "height": 337, "url": "https://forum.cheeseepedia.org/uploads/default/optimized/2X/5/5e4cbf41cc77a3392df25fdea3703cc35011d456_2_600x337.jpeg"}, {"max_width": 400, "max_height": 400, "width": 400, "height": 225, "url": "https://forum.cheeseepedia.org/uploads/default/optimized/2X/5/5e4cbf41cc77a3392df25fdea3703cc35011d456_2_400x225.jpeg"}, {"max_width": 300, "max_height": 300, "width": 300, "height": 168, "url": "https://forum.cheeseepedia.org/uploads/default/optimized/2X/5/5e4cbf41cc77a3392df25fdea3703cc35011d456_2_300x168.jpeg"}, {"max_width": 200, "max_height": 200, "width": 200, "height": 112, "url": "https://forum.cheeseepedia.org/uploads/default/optimized/2X/5/5e4cbf41cc77a3392df25fdea3703cc35011d456_2_200x112.jpeg"}], "tags": [], "tags_descriptions": {}, "views": 228, "like_count": 4, "has_summary": false, "last_poster_username": "CECR995", "category_id": 5, "op_like_count": 1, "pinned_globally": false, "featured_link": null, "has_accepted_answer": false, "can_vote": false, "posters": [{"extras": null, "description": "Original Poster", "user_id": 1, "primary_group_id": 41, "flair_group_id": 41}, {"extras": null, "description": "Frequent Poster", "user_id": 26, "primary_group_id": 41, "flair_group_id": 41}, {"extras": null, "description": "Frequent Poster", "user_id": 17, "primary_group_id": 41, "flair_group_id": 41}, {"extras": "latest", "description": "Most Recent Poster", "user_id": 65, "primary_group_id": 41, "flair_group_id": 41}]}, {"fancy_title": "Lost AAM Demo Tapes Released!", "id": 205, "title": "Lost AAM Demo Tapes Released!", "slug": "lost-aam-demo-tapes-released", "posts_count": 2, "reply_count": 0, "highest_post_number": 2, "image_url": "https://forum.cheeseepedia.org/uploads/default/optimized/2X/a/a7bea2c10f14df21eba0e10b437adcd6999b9387_2_1024x576.jpeg", "created_at": "2026-01-15T01:04:54.046Z", "last_posted_at": "2026-01-15T20:33:38.292Z", "bumped": true, "bumped_at": "2026-01-15T20:33:38.292Z", "archetype": "regular", "unseen": false, "pinned": false, "unpinned": null, "visible": true, "closed": false, "archived": false, "bookmarked": null, "liked": null, "thumbnails": [{"max_width": null, "max_height": null, "width": 1280, "height": 720, "url": "https://forum.cheeseepedia.org/uploads/default/original/2X/a/a7bea2c10f14df21eba0e10b437adcd6999b9387.jpeg"}, {"max_width": 1024, "max_height": 1024, "width": 1024, "height": 576, "url": "https://forum.cheeseepedia.org/uploads/default/optimized/2X/a/a7bea2c10f14df21eba0e10b437adcd6999b9387_2_1024x576.jpeg"}, {"max_width": 800, "max_height": 800, "width": 800, "height": 450, "url": "https://forum.cheeseepedia.org/uploads/default/optimized/2X/a/a7bea2c10f14df21eba0e10b437adcd6999b9387_2_800x450.jpeg"}, {"max_width": 600, "max_height": 600, "width": 600, "height": 337, "url": "https://forum.cheeseepedia.org/uploads/default/optimized/2X/a/a7bea2c10f14df21eba0e10b437adcd6999b9387_2_600x337.jpeg"}, {"max_width": 400, "max_height": 400, "width": 400, "height": 225, "url": "https://forum.cheeseepedia.org/uploads/default/optimized/2X/a/a7bea2c10f14df21eba0e10b437adcd6999b9387_2_400x225.jpeg"}, {"max_width": 300, "max_height": 300, "width": 300, "height": 168, "url": "https://forum.cheeseepedia.org/uploads/default/optimized/2X/a/a7bea2c10f14df21eba0e10b437adcd6999b9387_2_300x168.jpeg"}, {"max_width": 200, "max_height": 200, "width": 200, "height": 112, "url": "https://forum.cheeseepedia.org/uploads/default/optimized/2X/a/a7bea2c10f14df21eba0e10b437adcd6999b9387_2_200x112.jpeg"}], "tags": ["lost-media"], "tags_descriptions": {}, "views": 205, "like_count": 3, "has_summary": false, "last_poster_username": "randomguyfan22-maker", "category_id": 5, "op_like_count": 3, "pinned_globally": false, "featured_link": null, "has_accepted_answer": false, "can_vote": false, "posters": [{"extras": null, "description": "Original Poster", "user_id": 1, "primary_group_id": 41, "flair_group_id": 41}, {"extras": "latest", "description": "Most Recent Poster", "user_id": 26, "primary_group_id": 41, "flair_group_id": 41}]}, {"fancy_title": "David McKillips Continues Years Long Pajamas and Cereal Delusions", "id": 200, "title": "David McKillips Continues Years Long Pajamas and Cereal Delusions", "slug": "david-mckillips-continues-years-long-pajamas-and-cereal-delusions", "posts_count": 6, "reply_count": 1, "highest_post_number": 6, "image_url": "https://forum.cheeseepedia.org/uploads/default/optimized/2X/c/c44eeaab6359412ab2e77e4c1099db07e2a1abca_2_1024x766.jpeg", "created_at": "2026-01-12T00:11:59.158Z", "last_posted_at": "2026-01-18T20:24:10.337Z", "bumped": true, "bumped_at": "2026-01-18T20:24:10.337Z", "archetype": "regular", "unseen": false, "pinned": false, "unpinned": null, "visible": true, "closed": false, "archived": false, "bookmarked": null, "liked": null, "thumbnails": [{"max_width": null, "max_height": null, "width": 1284, "height": 961, "url": "https://forum.cheeseepedia.org/uploads/default/original/2X/c/c44eeaab6359412ab2e77e4c1099db07e2a1abca.jpeg"}, {"max_width": 1024, "max_height": 1024, "width": 1024, "height": 766, "url": "https://forum.cheeseepedia.org/uploads/default/optimized/2X/c/c44eeaab6359412ab2e77e4c1099db07e2a1abca_2_1024x766.jpeg"}, {"max_width": 800, "max_height": 800, "width": 800, "height": 598, "url": "https://forum.cheeseepedia.org/uploads/default/optimized/2X/c/c44eeaab6359412ab2e77e4c1099db07e2a1abca_2_800x598.jpeg"}, {"max_width": 600, "max_height": 600, "width": 600, "height": 449, "url": "https://forum.cheeseepedia.org/uploads/default/optimized/2X/c/c44eeaab6359412ab2e77e4c1099db07e2a1abca_2_600x449.jpeg"}, {"max_width": 400, "max_height": 400, "width": 400, "height": 299, "url": "https://forum.cheeseepedia.org/uploads/default/optimized/2X/c/c44eeaab6359412ab2e77e4c1099db07e2a1abca_2_400x299.jpeg"}, {"max_width": 300, "max_height": 300, "width": 300, "height": 224, "url": "https://forum.cheeseepedia.org/uploads/default/optimized/2X/c/c44eeaab6359412ab2e77e4c1099db07e2a1abca_2_300x224.jpeg"}, {"max_width": 200, "max_height": 200, "width": 200, "height": 149, "url": "https://forum.cheeseepedia.org/uploads/default/optimized/2X/c/c44eeaab6359412ab2e77e4c1099db07e2a1abca_2_200x149.jpeg"}], "tags": ["chuck-e-cheese", "bankruptcy-believers", "chucks-arcade"], "tags_descriptions": {}, "views": 373, "like_count": 7, "has_summary": false, "last_poster_username": "cmsentance-byte", "category_id": 5, "op_like_count": 4, "pinned_globally": false, "featured_link": null, "has_accepted_answer": false, "can_vote": false, "posters": [{"extras": null, "description": "Original Poster", "user_id": 1, "primary_group_id": 41, "flair_group_id": 41}, {"extras": null, "description": "Frequent Poster", "user_id": 25, "primary_group_id": null, "flair_group_id": null}, {"extras": null, "description": "Frequent Poster", "user_id": 26, "primary_group_id": 41, "flair_group_id": 41}, {"extras": null, "description": "Frequent Poster", "user_id": 65, "primary_group_id": 41, "flair_group_id": 41}, {"extras": "latest", "description": "Most Recent Poster", "user_id": 61, "primary_group_id": null, "flair_group_id": null}]}, {"fancy_title": "Topic of the Month Returns: Merchandise Month!", "id": 199, "title": "Topic of the Month Returns: Merchandise Month!", "slug": "topic-of-the-month-returns-merchandise-month", "posts_count": 4, "reply_count": 0, "highest_post_number": 4, "image_url": "https://forum.cheeseepedia.org/uploads/default/optimized/2X/c/ca2675c3688df34fa22f563dd9dbc089adf40bc9_2_1024x989.jpeg", "created_at": "2026-01-11T00:37:36.722Z", "last_posted_at": "2026-01-31T23:04:11.070Z", "bumped": true, "bumped_at": "2026-01-31T23:04:11.070Z", "archetype": "regular", "unseen": false, "pinned": false, "unpinned": null, "visible": true, "closed": false, "archived": false, "bookmarked": null, "liked": null, "thumbnails": [{"max_width": null, "max_height": null, "width": 1464, "height": 1414, "url": "https://forum.cheeseepedia.org/uploads/default/original/2X/c/ca2675c3688df34fa22f563dd9dbc089adf40bc9.jpeg"}, {"max_width": 1024, "max_height": 1024, "width": 1024, "height": 989, "url": "https://forum.cheeseepedia.org/uploads/default/optimized/2X/c/ca2675c3688df34fa22f563dd9dbc089adf40bc9_2_1024x989.jpeg"}, {"max_width": 800, "max_height": 800, "width": 800, "height": 772, "url": "https://forum.cheeseepedia.org/uploads/default/optimized/2X/c/ca2675c3688df34fa22f563dd9dbc089adf40bc9_2_800x772.jpeg"}, {"max_width": 600, "max_height": 600, "width": 600, "height": 579, "url": "https://forum.cheeseepedia.org/uploads/default/optimized/2X/c/ca2675c3688df34fa22f563dd9dbc089adf40bc9_2_600x579.jpeg"}, {"max_width": 400, "max_height": 400, "width": 400, "height": 386, "url": "https://forum.cheeseepedia.org/uploads/default/optimized/2X/c/ca2675c3688df34fa22f563dd9dbc089adf40bc9_2_400x386.jpeg"}, {"max_width": 300, "max_height": 300, "width": 300, "height": 289, "url": "https://forum.cheeseepedia.org/uploads/default/optimized/2X/c/ca2675c3688df34fa22f563dd9dbc089adf40bc9_2_300x289.jpeg"}, {"max_width": 200, "max_height": 200, "width": 200, "height": 193, "url": "https://forum.cheeseepedia.org/uploads/default/optimized/2X/c/ca2675c3688df34fa22f563dd9dbc089adf40bc9_2_200x193.jpeg"}], "tags": ["lost-media", "cheese-e-pedia", "topic-of-the-month"], "tags_descriptions": {}, "views": 176, "like_count": 3, "has_summary": false, "last_poster_username": "The-64th-Gamer", "category_id": 5, "op_like_count": 1, "pinned_globally": false, "featured_link": null, "has_accepted_answer": false, "can_vote": false, "posters": [{"extras": "latest", "description": "Original Poster, Most Recent Poster", "user_id": 1, "primary_group_id": 41, "flair_group_id": 41}, {"extras": null, "description": "Frequent Poster", "user_id": 76, "primary_group_id": null, "flair_group_id": null}]}, {"fancy_title": "New Wiki Search Replaces Pagefind", "id": 197, "title": "New Wiki Search Replaces Pagefind", "slug": "new-wiki-search-replaces-pagefind", "posts_count": 5, "reply_count": 0, "highest_post_number": 5, "image_url": "https://forum.cheeseepedia.org/uploads/default/optimized/2X/6/61d951942efc5fcd64eb2e2fe57f6d8b7135b3fb_2_1024x684.png", "created_at": "2026-01-09T02:57:43.844Z", "last_posted_at": "2026-01-28T01:47:36.721Z", "bumped": true, "bumped_at": "2026-01-28T01:47:36.721Z", "archetype": "regular", "unseen": false, "pinned": false, "unpinned": null, "visible": true, "closed": false, "archived": false, "bookmarked": null, "liked": null, "thumbnails": [{"max_width": null, "max_height": null, "width": 1111, "height": 743, "url": "https://forum.cheeseepedia.org/uploads/default/original/2X/6/61d951942efc5fcd64eb2e2fe57f6d8b7135b3fb.png"}, {"max_width": 1024, "max_height": 1024, "width": 1024, "height": 684, "url": "https://forum.cheeseepedia.org/uploads/default/optimized/2X/6/61d951942efc5fcd64eb2e2fe57f6d8b7135b3fb_2_1024x684.png"}, {"max_width": 800, "max_height": 800, "width": 800, "height": 535, "url": "https://forum.cheeseepedia.org/uploads/default/optimized/2X/6/61d951942efc5fcd64eb2e2fe57f6d8b7135b3fb_2_800x535.png"}, {"max_width": 600, "max_height": 600, "width": 600, "height": 401, "url": "https://forum.cheeseepedia.org/uploads/default/optimized/2X/6/61d951942efc5fcd64eb2e2fe57f6d8b7135b3fb_2_600x401.png"}, {"max_width": 400, "max_height": 400, "width": 400, "height": 267, "url": "https://forum.cheeseepedia.org/uploads/default/optimized/2X/6/61d951942efc5fcd64eb2e2fe57f6d8b7135b3fb_2_400x267.png"}, {"max_width": 300, "max_height": 300, "width": 300, "height": 200, "url": "https://forum.cheeseepedia.org/uploads/default/optimized/2X/6/61d951942efc5fcd64eb2e2fe57f6d8b7135b3fb_2_300x200.png"}, {"max_width": 200, "max_height": 200, "width": 200, "height": 133, "url": "https://forum.cheeseepedia.org/uploads/default/optimized/2X/6/61d951942efc5fcd64eb2e2fe57f6d8b7135b3fb_2_200x133.png"}], "tags": ["cheese-e-pedia"], "tags_descriptions": {}, "views": 150, "like_count": 3, "has_summary": false, "last_poster_username": "The-64th-Gamer", "category_id": 5, "op_like_count": 1, "pinned_globally": false, "featured_link": null, "has_accepted_answer": false, "can_vote": false, "posters": [{"extras": "latest", "description": "Original Poster, Most Recent Poster", "user_id": 1, "primary_group_id": 41, "flair_group_id": 41}, {"extras": null, "description": "Frequent Poster", "user_id": 26, "primary_group_id": 41, "flair_group_id": 41}]}, {"fancy_title": "Kansas City Closes for the 3rd Time!", "id": 196, "title": "Kansas City Closes for the 3rd Time!", "slug": "kansas-city-closes-for-the-3rd-time", "posts_count": 6, "reply_count": 1, "highest_post_number": 6, "image_url": "https://forum.cheeseepedia.org/uploads/default/original/2X/e/edb6b8b9ff3aa2812eda2e7684ddc59b916aa095.jpeg", "created_at": "2026-01-06T17:32:56.002Z", "last_posted_at": "2026-01-09T00:33:44.523Z", "bumped": true, "bumped_at": "2026-01-09T00:33:44.523Z", "archetype": "regular", "unseen": false, "pinned": false, "unpinned": null, "visible": true, "closed": false, "archived": false, "bookmarked": null, "liked": null, "thumbnails": [{"max_width": null, "max_height": null, "width": 596, "height": 267, "url": "https://forum.cheeseepedia.org/uploads/default/original/2X/e/edb6b8b9ff3aa2812eda2e7684ddc59b916aa095.jpeg"}, {"max_width": 400, "max_height": 400, "width": 400, "height": 179, "url": "https://forum.cheeseepedia.org/uploads/default/optimized/2X/e/edb6b8b9ff3aa2812eda2e7684ddc59b916aa095_2_400x179.jpeg"}, {"max_width": 300, "max_height": 300, "width": 300, "height": 134, "url": "https://forum.cheeseepedia.org/uploads/default/optimized/2X/e/edb6b8b9ff3aa2812eda2e7684ddc59b916aa095_2_300x134.jpeg"}, {"max_width": 200, "max_height": 200, "width": 200, "height": 89, "url": "https://forum.cheeseepedia.org/uploads/default/optimized/2X/e/edb6b8b9ff3aa2812eda2e7684ddc59b916aa095_2_200x89.jpeg"}], "tags": ["chuck-e-cheese", "bankruptcy-believers", "chucks-arcade"], "tags_descriptions": {}, "views": 435, "like_count": 3, "has_summary": false, "last_poster_username": "The-64th-Gamer", "category_id": 5, "op_like_count": 1, "pinned_globally": false, "featured_link": null, "has_accepted_answer": false, "can_vote": false, "posters": [{"extras": "latest", "description": "Original Poster, Most Recent Poster", "user_id": 1, "primary_group_id": 41, "flair_group_id": 41}, {"extras": null, "description": "Frequent Poster", "user_id": 19, "primary_group_id": null, "flair_group_id": null}, {"extras": null, "description": "Frequent Poster", "user_id": 25, "primary_group_id": null, "flair_group_id": null}]}, {"fancy_title": "CEP Graphs &amp; Improvements!", "id": 194, "title": "CEP Graphs & Improvements!", "slug": "cep-graphs-improvements", "posts_count": 2, "reply_count": 0, "highest_post_number": 2, "image_url": "https://forum.cheeseepedia.org/uploads/default/optimized/1X/40dd59a23cf55571b76ec39c40504938a1b049a8_2_1024x462.png", "created_at": "2026-01-03T18:38:07.253Z", "last_posted_at": "2026-01-04T10:25:39.807Z", "bumped": true, "bumped_at": "2026-01-04T10:25:39.807Z", "archetype": "regular", "unseen": false, "pinned": false, "unpinned": null, "visible": true, "closed": false, "archived": false, "bookmarked": null, "liked": null, "thumbnails": [{"max_width": null, "max_height": null, "width": 1057, "height": 477, "url": "https://forum.cheeseepedia.org/uploads/default/original/1X/40dd59a23cf55571b76ec39c40504938a1b049a8.png"}, {"max_width": 1024, "max_height": 1024, "width": 1024, "height": 462, "url": "https://forum.cheeseepedia.org/uploads/default/optimized/1X/40dd59a23cf55571b76ec39c40504938a1b049a8_2_1024x462.png"}, {"max_width": 800, "max_height": 800, "width": 800, "height": 361, "url": "https://forum.cheeseepedia.org/uploads/default/optimized/1X/40dd59a23cf55571b76ec39c40504938a1b049a8_2_800x361.png"}, {"max_width": 600, "max_height": 600, "width": 600, "height": 270, "url": "https://forum.cheeseepedia.org/uploads/default/optimized/1X/40dd59a23cf55571b76ec39c40504938a1b049a8_2_600x270.png"}, {"max_width": 400, "max_height": 400, "width": 400, "height": 180, "url": "https://forum.cheeseepedia.org/uploads/default/optimized/1X/40dd59a23cf55571b76ec39c40504938a1b049a8_2_400x180.png"}, {"max_width": 300, "max_height": 300, "width": 300, "height": 135, "url": "https://forum.cheeseepedia.org/uploads/default/optimized/1X/40dd59a23cf55571b76ec39c40504938a1b049a8_2_300x135.png"}, {"max_width": 200, "max_height": 200, "width": 200, "height": 90, "url": "https://forum.cheeseepedia.org/uploads/default/optimized/1X/40dd59a23cf55571b76ec39c40504938a1b049a8_2_200x90.png"}], "tags": ["cheese-e-pedia"], "tags_descriptions": {}, "views": 118, "like_count": 1, "has_summary": false, "last_poster_username": "The-64th-Gamer", "category_id": 5, "op_like_count": 1, "pinned_globally": false, "featured_link": null, "has_accepted_answer": false, "can_vote": false, "posters": [{"extras": "latest single", "description": "Original Poster, Most Recent Poster", "user_id": 1, "primary_group_id": 41, "flair_group_id": 41}]}, {"fancy_title": "7 Mins of Concord, 17 Mins of New Kooser Footage", "id": 193, "title": "7 Mins of Concord, 17 Mins of New Kooser Footage", "slug": "7-mins-of-concord-17-mins-of-new-kooser-footage", "posts_count": 4, "reply_count": 2, "highest_post_number": 4, "image_url": "https://forum.cheeseepedia.org/uploads/default/optimized/1X/0f63e4a75f2b4b4ad2e91e930618b2b82a79123a_2_1024x665.jpeg", "created_at": "2026-01-02T01:50:25.755Z", "last_posted_at": "2026-01-18T00:06:38.541Z", "bumped": true, "bumped_at": "2026-01-18T00:06:38.541Z", "archetype": "regular", "unseen": false, "pinned": false, "unpinned": null, "visible": true, "closed": false, "archived": false, "bookmarked": null, "liked": null, "thumbnails": [{"max_width": null, "max_height": null, "width": 1186, "height": 771, "url": "https://forum.cheeseepedia.org/uploads/default/original/1X/0f63e4a75f2b4b4ad2e91e930618b2b82a79123a.jpeg"}, {"max_width": 1024, "max_height": 1024, "width": 1024, "height": 665, "url": "https://forum.cheeseepedia.org/uploads/default/optimized/1X/0f63e4a75f2b4b4ad2e91e930618b2b82a79123a_2_1024x665.jpeg"}, {"max_width": 800, "max_height": 800, "width": 800, "height": 520, "url": "https://forum.cheeseepedia.org/uploads/default/optimized/1X/0f63e4a75f2b4b4ad2e91e930618b2b82a79123a_2_800x520.jpeg"}, {"max_width": 600, "max_height": 600, "width": 600, "height": 390, "url": "https://forum.cheeseepedia.org/uploads/default/optimized/1X/0f63e4a75f2b4b4ad2e91e930618b2b82a79123a_2_600x390.jpeg"}, {"max_width": 400, "max_height": 400, "width": 400, "height": 260, "url": "https://forum.cheeseepedia.org/uploads/default/optimized/1X/0f63e4a75f2b4b4ad2e91e930618b2b82a79123a_2_400x260.jpeg"}, {"max_width": 300, "max_height": 300, "width": 300, "height": 195, "url": "https://forum.cheeseepedia.org/uploads/default/optimized/1X/0f63e4a75f2b4b4ad2e91e930618b2b82a79123a_2_300x195.jpeg"}, {"max_width": 200, "max_height": 200, "width": 200, "height": 130, "url": "https://forum.cheeseepedia.org/uploads/default/optimized/1X/0f63e4a75f2b4b4ad2e91e930618b2b82a79123a_2_200x130.jpeg"}], "tags": ["lost-media"], "tags_descriptions": {}, "views": 379, "like_count": 2, "has_summary": false, "last_poster_username": "CECR995", "category_id": 5, "op_like_count": 1, "pinned_globally": false, "featured_link": null, "has_accepted_answer": false, "can_vote": false, "posters": [{"extras": null, "description": "Original Poster", "user_id": 1, "primary_group_id": 41, "flair_group_id": 41}, {"extras": null, "description": "Frequent Poster", "user_id": 16, "primary_group_id": null, "flair_group_id": null}, {"extras": "latest", "description": "Most Recent Poster", "user_id": 65, "primary_group_id": 41, "flair_group_id": 41}]}, {"fancy_title": "Early Cut of April 1996 Show Released!", "id": 192, "title": "Early Cut of April 1996 Show Released!", "slug": "early-cut-of-april-1996-show-released", "posts_count": 1, "reply_count": 0, "highest_post_number": 1, "image_url": "https://forum.cheeseepedia.org/uploads/default/optimized/1X/e5f632cb437bb0e243b15386effa6162f8092c4a_2_1024x576.jpeg", "created_at": "2026-01-01T21:14:59.033Z", "last_posted_at": "2026-01-01T21:14:59.211Z", "bumped": true, "bumped_at": "2026-01-01T21:14:59.211Z", "archetype": "regular", "unseen": false, "pinned": false, "unpinned": null, "visible": true, "closed": false, "archived": false, "bookmarked": null, "liked": null, "thumbnails": [{"max_width": null, "max_height": null, "width": 1280, "height": 720, "url": "https://forum.cheeseepedia.org/uploads/default/original/1X/e5f632cb437bb0e243b15386effa6162f8092c4a.jpeg"}, {"max_width": 1024, "max_height": 1024, "width": 1024, "height": 576, "url": "https://forum.cheeseepedia.org/uploads/default/optimized/1X/e5f632cb437bb0e243b15386effa6162f8092c4a_2_1024x576.jpeg"}, {"max_width": 800, "max_height": 800, "width": 800, "height": 450, "url": "https://forum.cheeseepedia.org/uploads/default/optimized/1X/e5f632cb437bb0e243b15386effa6162f8092c4a_2_800x450.jpeg"}, {"max_width": 600, "max_height": 600, "width": 600, "height": 337, "url": "https://forum.cheeseepedia.org/uploads/default/optimized/1X/e5f632cb437bb0e243b15386effa6162f8092c4a_2_600x337.jpeg"}, {"max_width": 400, "max_height": 400, "width": 400, "height": 225, "url": "https://forum.cheeseepedia.org/uploads/default/optimized/1X/e5f632cb437bb0e243b15386effa6162f8092c4a_2_400x225.jpeg"}, {"max_width": 300, "max_height": 300, "width": 300, "height": 168, "url": "https://forum.cheeseepedia.org/uploads/default/optimized/1X/e5f632cb437bb0e243b15386effa6162f8092c4a_2_300x168.jpeg"}, {"max_width": 200, "max_height": 200, "width": 200, "height": 112, "url": "https://forum.cheeseepedia.org/uploads/default/optimized/1X/e5f632cb437bb0e243b15386effa6162f8092c4a_2_200x112.jpeg"}], "tags": ["lost-media"], "tags_descriptions": {}, "views": 164, "like_count": 4, "has_summary": false, "last_poster_username": "The-64th-Gamer", "category_id": 5, "op_like_count": 4, "pinned_globally": false, "featured_link": null, "has_accepted_answer": false, "can_vote": false, "posters": [{"extras": "latest single", "description": "Original Poster, Most Recent Poster", "user_id": 1, "primary_group_id": 41, "flair_group_id": 41}]}, {"fancy_title": "Lost RAE 90&rsquo;s Song &lsquo;Someday&rsquo; Found!", "id": 191, "title": "Lost RAE 90's Song 'Someday' Found!", "slug": "lost-rae-90s-song-someday-found", "posts_count": 1, "reply_count": 0, "highest_post_number": 1, "image_url": "https://forum.cheeseepedia.org/uploads/default/optimized/1X/a528bf72ac3b0e72afd95e363ccd91824cfd6ca5_2_1024x576.jpeg", "created_at": "2025-12-28T22:21:11.676Z", "last_posted_at": "2025-12-28T22:21:11.792Z", "bumped": true, "bumped_at": "2025-12-28T22:21:11.792Z", "archetype": "regular", "unseen": false, "pinned": false, "unpinned": null, "visible": true, "closed": false, "archived": false, "bookmarked": null, "liked": null, "thumbnails": [{"max_width": null, "max_height": null, "width": 1280, "height": 720, "url": "https://forum.cheeseepedia.org/uploads/default/original/1X/a528bf72ac3b0e72afd95e363ccd91824cfd6ca5.jpeg"}, {"max_width": 1024, "max_height": 1024, "width": 1024, "height": 576, "url": "https://forum.cheeseepedia.org/uploads/default/optimized/1X/a528bf72ac3b0e72afd95e363ccd91824cfd6ca5_2_1024x576.jpeg"}, {"max_width": 800, "max_height": 800, "width": 800, "height": 450, "url": "https://forum.cheeseepedia.org/uploads/default/optimized/1X/a528bf72ac3b0e72afd95e363ccd91824cfd6ca5_2_800x450.jpeg"}, {"max_width": 600, "max_height": 600, "width": 600, "height": 337, "url": "https://forum.cheeseepedia.org/uploads/default/optimized/1X/a528bf72ac3b0e72afd95e363ccd91824cfd6ca5_2_600x337.jpeg"}, {"max_width": 400, "max_height": 400, "width": 400, "height": 225, "url": "https://forum.cheeseepedia.org/uploads/default/optimized/1X/a528bf72ac3b0e72afd95e363ccd91824cfd6ca5_2_400x225.jpeg"}, {"max_width": 300, "max_height": 300, "width": 300, "height": 168, "url": "https://forum.cheeseepedia.org/uploads/default/optimized/1X/a528bf72ac3b0e72afd95e363ccd91824cfd6ca5_2_300x168.jpeg"}, {"max_width": 200, "max_height": 200, "width": 200, "height": 112, "url": "https://forum.cheeseepedia.org/uploads/default/optimized/1X/a528bf72ac3b0e72afd95e363ccd91824cfd6ca5_2_200x112.jpeg"}], "tags": ["lost-media", "showbiz-pizza-place", "rock-afire-explosion"], "tags_descriptions": {}, "views": 245, "like_count": 2, "has_summary": false, "last_poster_username": "The-64th-Gamer", "category_id": 5, "op_like_count": 2, "pinned_globally": false, "featured_link": null, "has_accepted_answer": false, "can_vote": false, "posters": [{"extras": "latest single", "description": "Original Poster, Most Recent Poster", "user_id": 1, "primary_group_id": 41, "flair_group_id": 41}]}, {"fancy_title": "New Rock-Afire Christmas Showtape! (22 min)", "id": 188, "title": "New Rock-Afire Christmas Showtape! (22 min)", "slug": "new-rock-afire-christmas-showtape-22-min", "posts_count": 1, "reply_count": 0, "highest_post_number": 1, "image_url": "https://forum.cheeseepedia.org/uploads/default/optimized/1X/c9a10a4c19262481bc15a7d1d9f63b88c2c6ef81_2_1024x576.jpeg", "created_at": "2025-12-26T01:15:00.671Z", "last_posted_at": "2025-12-26T01:15:00.891Z", "bumped": true, "bumped_at": "2025-12-26T01:15:00.891Z", "archetype": "regular", "unseen": false, "pinned": false, "unpinned": null, "visible": true, "closed": false, "archived": false, "bookmarked": null, "liked": null, "thumbnails": [{"max_width": null, "max_height": null, "width": 1280, "height": 720, "url": "https://forum.cheeseepedia.org/uploads/default/original/1X/c9a10a4c19262481bc15a7d1d9f63b88c2c6ef81.jpeg"}, {"max_width": 1024, "max_height": 1024, "width": 1024, "height": 576, "url": "https://forum.cheeseepedia.org/uploads/default/optimized/1X/c9a10a4c19262481bc15a7d1d9f63b88c2c6ef81_2_1024x576.jpeg"}, {"max_width": 800, "max_height": 800, "width": 800, "height": 450, "url": "https://forum.cheeseepedia.org/uploads/default/optimized/1X/c9a10a4c19262481bc15a7d1d9f63b88c2c6ef81_2_800x450.jpeg"}, {"max_width": 600, "max_height": 600, "width": 600, "height": 337, "url": "https://forum.cheeseepedia.org/uploads/default/optimized/1X/c9a10a4c19262481bc15a7d1d9f63b88c2c6ef81_2_600x337.jpeg"}, {"max_width": 400, "max_height": 400, "width": 400, "height": 225, "url": "https://forum.cheeseepedia.org/uploads/default/optimized/1X/c9a10a4c19262481bc15a7d1d9f63b88c2c6ef81_2_400x225.jpeg"}, {"max_width": 300, "max_height": 300, "width": 300, "height": 168, "url": "https://forum.cheeseepedia.org/uploads/default/optimized/1X/c9a10a4c19262481bc15a7d1d9f63b88c2c6ef81_2_300x168.jpeg"}, {"max_width": 200, "max_height": 200, "width": 200, "height": 112, "url": "https://forum.cheeseepedia.org/uploads/default/optimized/1X/c9a10a4c19262481bc15a7d1d9f63b88c2c6ef81_2_200x112.jpeg"}], "tags": ["showbiz-pizza-place", "rock-afire-explosion", "simulator", "creative-engineering"], "tags_descriptions": {}, "views": 139, "like_count": 1, "has_summary": false, "last_poster_username": "The-64th-Gamer", "category_id": 5, "op_like_count": 1, "pinned_globally": false, "featured_link": null, "has_accepted_answer": false, "can_vote": false, "posters": [{"extras": "latest single", "description": "Original Poster, Most Recent Poster", "user_id": 1, "primary_group_id": 41, "flair_group_id": 41}]}, {"fancy_title": "Surprise Interview with Crusty and King&rsquo;s Original VA!", "id": 187, "title": "Surprise Interview with Crusty and King's Original VA!", "slug": "surprise-interview-with-crusty-and-kings-original-va", "posts_count": 1, "reply_count": 0, "highest_post_number": 1, "image_url": "https://forum.cheeseepedia.org/uploads/default/optimized/1X/d5100937ced2a22792e8ab6f918a51fd4cd7cc09_2_1024x576.jpeg", "created_at": "2025-12-25T07:11:07.442Z", "last_posted_at": "2025-12-25T07:11:07.624Z", "bumped": true, "bumped_at": "2025-12-25T07:11:07.624Z", "archetype": "regular", "unseen": false, "pinned": false, "unpinned": null, "visible": true, "closed": false, "archived": false, "bookmarked": null, "liked": null, "thumbnails": [{"max_width": null, "max_height": null, "width": 1280, "height": 720, "url": "https://forum.cheeseepedia.org/uploads/default/original/1X/d5100937ced2a22792e8ab6f918a51fd4cd7cc09.jpeg"}, {"max_width": 1024, "max_height": 1024, "width": 1024, "height": 576, "url": "https://forum.cheeseepedia.org/uploads/default/optimized/1X/d5100937ced2a22792e8ab6f918a51fd4cd7cc09_2_1024x576.jpeg"}, {"max_width": 800, "max_height": 800, "width": 800, "height": 450, "url": "https://forum.cheeseepedia.org/uploads/default/optimized/1X/d5100937ced2a22792e8ab6f918a51fd4cd7cc09_2_800x450.jpeg"}, {"max_width": 600, "max_height": 600, "width": 600, "height": 337, "url": "https://forum.cheeseepedia.org/uploads/default/optimized/1X/d5100937ced2a22792e8ab6f918a51fd4cd7cc09_2_600x337.jpeg"}, {"max_width": 400, "max_height": 400, "width": 400, "height": 225, "url": "https://forum.cheeseepedia.org/uploads/default/optimized/1X/d5100937ced2a22792e8ab6f918a51fd4cd7cc09_2_400x225.jpeg"}, {"max_width": 300, "max_height": 300, "width": 300, "height": 168, "url": "https://forum.cheeseepedia.org/uploads/default/optimized/1X/d5100937ced2a22792e8ab6f918a51fd4cd7cc09_2_300x168.jpeg"}, {"max_width": 200, "max_height": 200, "width": 200, "height": 112, "url": "https://forum.cheeseepedia.org/uploads/default/optimized/1X/d5100937ced2a22792e8ab6f918a51fd4cd7cc09_2_200x112.jpeg"}], "tags": ["pizza-time-theatre", "lost-media"], "tags_descriptions": {}, "views": 169, "like_count": 1, "has_summary": false, "last_poster_username": "The-64th-Gamer", "category_id": 5, "op_like_count": 1, "pinned_globally": false, "featured_link": null, "has_accepted_answer": false, "can_vote": false, "posters": [{"extras": "latest single", "description": "Original Poster, Most Recent Poster", "user_id": 1, "primary_group_id": 41, "flair_group_id": 41}]}, {"fancy_title": "FYI Live Show Interview 1992 w/ More Montfort Footage Found!", "id": 179, "title": "FYI Live Show Interview 1992 w/ More Montfort Footage Found!", "slug": "fyi-live-show-interview-1992-w-more-montfort-footage-found", "posts_count": 1, "reply_count": 0, "highest_post_number": 1, "image_url": "https://forum.cheeseepedia.org/uploads/default/optimized/1X/07f4e93154723837497394b79815b4dcaa2e9819_2_1024x576.jpeg", "created_at": "2025-12-18T21:29:24.414Z", "last_posted_at": "2025-12-18T21:29:24.577Z", "bumped": true, "bumped_at": "2025-12-18T21:29:24.577Z", "archetype": "regular", "unseen": false, "pinned": false, "unpinned": null, "visible": true, "closed": false, "archived": false, "bookmarked": null, "liked": null, "thumbnails": [{"max_width": null, "max_height": null, "width": 1280, "height": 720, "url": "https://forum.cheeseepedia.org/uploads/default/original/1X/07f4e93154723837497394b79815b4dcaa2e9819.jpeg"}, {"max_width": 1024, "max_height": 1024, "width": 1024, "height": 576, "url": "https://forum.cheeseepedia.org/uploads/default/optimized/1X/07f4e93154723837497394b79815b4dcaa2e9819_2_1024x576.jpeg"}, {"max_width": 800, "max_height": 800, "width": 800, "height": 450, "url": "https://forum.cheeseepedia.org/uploads/default/optimized/1X/07f4e93154723837497394b79815b4dcaa2e9819_2_800x450.jpeg"}, {"max_width": 600, "max_height": 600, "width": 600, "height": 337, "url": "https://forum.cheeseepedia.org/uploads/default/optimized/1X/07f4e93154723837497394b79815b4dcaa2e9819_2_600x337.jpeg"}, {"max_width": 400, "max_height": 400, "width": 400, "height": 225, "url": "https://forum.cheeseepedia.org/uploads/default/optimized/1X/07f4e93154723837497394b79815b4dcaa2e9819_2_400x225.jpeg"}, {"max_width": 300, "max_height": 300, "width": 300, "height": 168, "url": "https://forum.cheeseepedia.org/uploads/default/optimized/1X/07f4e93154723837497394b79815b4dcaa2e9819_2_300x168.jpeg"}, {"max_width": 200, "max_height": 200, "width": 200, "height": 112, "url": "https://forum.cheeseepedia.org/uploads/default/optimized/1X/07f4e93154723837497394b79815b4dcaa2e9819_2_200x112.jpeg"}], "tags": ["lost-media"], "tags_descriptions": {}, "views": 227, "like_count": 1, "has_summary": false, "last_poster_username": "The-64th-Gamer", "category_id": 5, "op_like_count": 1, "pinned_globally": false, "featured_link": null, "has_accepted_answer": false, "can_vote": false, "posters": [{"extras": "latest single", "description": "Original Poster, Most Recent Poster", "user_id": 1, "primary_group_id": 41, "flair_group_id": 41}]}, {"fancy_title": "New Retro CEC Merchandise", "id": 178, "title": "New Retro CEC Merchandise", "slug": "new-retro-cec-merchandise", "posts_count": 1, "reply_count": 0, "highest_post_number": 1, "image_url": "https://forum.cheeseepedia.org/uploads/default/original/1X/90ea6b7308e260b629341cadae195601966dccb8.jpeg", "created_at": "2025-12-18T21:28:07.832Z", "last_posted_at": "2025-12-18T21:28:08.066Z", "bumped": true, "bumped_at": "2025-12-18T21:28:08.066Z", "archetype": "regular", "unseen": false, "pinned": false, "unpinned": null, "visible": true, "closed": false, "archived": false, "bookmarked": null, "liked": null, "thumbnails": [{"max_width": null, "max_height": null, "width": 500, "height": 500, "url": "https://forum.cheeseepedia.org/uploads/default/original/1X/90ea6b7308e260b629341cadae195601966dccb8.jpeg"}, {"max_width": 400, "max_height": 400, "width": 400, "height": 400, "url": "https://forum.cheeseepedia.org/uploads/default/optimized/1X/90ea6b7308e260b629341cadae195601966dccb8_2_400x400.jpeg"}, {"max_width": 300, "max_height": 300, "width": 300, "height": 300, "url": "https://forum.cheeseepedia.org/uploads/default/optimized/1X/90ea6b7308e260b629341cadae195601966dccb8_2_300x300.jpeg"}, {"max_width": 200, "max_height": 200, "width": 200, "height": 200, "url": "https://forum.cheeseepedia.org/uploads/default/optimized/1X/90ea6b7308e260b629341cadae195601966dccb8_2_200x200.jpeg"}], "tags": ["chuck-e-cheese", "pizza-time-theatre", "bankruptcy-believers"], "tags_descriptions": {}, "views": 88, "like_count": 1, "has_summary": false, "last_poster_username": "The-64th-Gamer", "category_id": 5, "op_like_count": 1, "pinned_globally": false, "featured_link": null, "has_accepted_answer": false, "can_vote": false, "posters": [{"extras": "latest single", "description": "Original Poster, Most Recent Poster", "user_id": 1, "primary_group_id": 41, "flair_group_id": 41}]}, {"fancy_title": "CEP Homepage &amp; Compiling Improvements", "id": 177, "title": "CEP Homepage & Compiling Improvements", "slug": "cep-homepage-compiling-improvements", "posts_count": 1, "reply_count": 0, "highest_post_number": 1, "image_url": "https://forum.cheeseepedia.org/uploads/default/optimized/1X/2d9570f991dcf47ae87d80db2eb107b0992f9c98_2_1024x417.png", "created_at": "2025-12-18T08:00:53.295Z", "last_posted_at": "2025-12-18T08:00:53.499Z", "bumped": true, "bumped_at": "2025-12-18T08:00:53.499Z", "archetype": "regular", "unseen": false, "pinned": false, "unpinned": null, "visible": true, "closed": false, "archived": false, "bookmarked": null, "liked": null, "thumbnails": [{"max_width": null, "max_height": null, "width": 1089, "height": 444, "url": "https://forum.cheeseepedia.org/uploads/default/original/1X/2d9570f991dcf47ae87d80db2eb107b0992f9c98.png"}, {"max_width": 1024, "max_height": 1024, "width": 1024, "height": 417, "url": "https://forum.cheeseepedia.org/uploads/default/optimized/1X/2d9570f991dcf47ae87d80db2eb107b0992f9c98_2_1024x417.png"}, {"max_width": 800, "max_height": 800, "width": 799, "height": 326, "url": "https://forum.cheeseepedia.org/uploads/default/optimized/1X/2d9570f991dcf47ae87d80db2eb107b0992f9c98_2_799x326.png"}, {"max_width": 600, "max_height": 600, "width": 600, "height": 244, "url": "https://forum.cheeseepedia.org/uploads/default/optimized/1X/2d9570f991dcf47ae87d80db2eb107b0992f9c98_2_600x244.png"}, {"max_width": 400, "max_height": 400, "width": 399, "height": 163, "url": "https://forum.cheeseepedia.org/uploads/default/optimized/1X/2d9570f991dcf47ae87d80db2eb107b0992f9c98_2_399x163.png"}, {"max_width": 300, "max_height": 300, "width": 300, "height": 122, "url": "https://forum.cheeseepedia.org/uploads/default/optimized/1X/2d9570f991dcf47ae87d80db2eb107b0992f9c98_2_300x122.png"}, {"max_width": 200, "max_height": 200, "width": 199, "height": 81, "url": "https://forum.cheeseepedia.org/uploads/default/optimized/1X/2d9570f991dcf47ae87d80db2eb107b0992f9c98_2_199x81.png"}], "tags": ["cheese-e-pedia"], "tags_descriptions": {}, "views": 64, "like_count": 3, "has_summary": false, "last_poster_username": "The-64th-Gamer", "category_id": 5, "op_like_count": 3, "pinned_globally": false, "featured_link": null, "has_accepted_answer": false, "can_vote": false, "posters": [{"extras": "latest single", "description": "Original Poster, Most Recent Poster", "user_id": 1, "primary_group_id": 41, "flair_group_id": 41}]}, {"fancy_title": "NEW Awesome Adventure Machine Footage!", "id": 173, "title": "NEW Awesome Adventure Machine Footage!", "slug": "new-awesome-adventure-machine-footage", "posts_count": 4, "reply_count": 0, "highest_post_number": 4, "image_url": "https://forum.cheeseepedia.org/uploads/default/original/1X/2e1d154c3a7c4af64c536c30dbdb1b4bf5af01ab.jpeg", "created_at": "2025-12-16T22:08:57.629Z", "last_posted_at": "2025-12-18T01:44:56.254Z", "bumped": true, "bumped_at": "2025-12-18T01:44:56.254Z", "archetype": "regular", "unseen": false, "pinned": false, "unpinned": null, "visible": true, "closed": false, "archived": false, "bookmarked": null, "liked": null, "thumbnails": [{"max_width": null, "max_height": null, "width": 579, "height": 406, "url": "https://forum.cheeseepedia.org/uploads/default/original/1X/2e1d154c3a7c4af64c536c30dbdb1b4bf5af01ab.jpeg"}, {"max_width": 400, "max_height": 400, "width": 400, "height": 280, "url": "https://forum.cheeseepedia.org/uploads/default/optimized/1X/2e1d154c3a7c4af64c536c30dbdb1b4bf5af01ab_2_400x280.jpeg"}, {"max_width": 300, "max_height": 300, "width": 300, "height": 210, "url": "https://forum.cheeseepedia.org/uploads/default/optimized/1X/2e1d154c3a7c4af64c536c30dbdb1b4bf5af01ab_2_300x210.jpeg"}, {"max_width": 200, "max_height": 200, "width": 200, "height": 140, "url": "https://forum.cheeseepedia.org/uploads/default/optimized/1X/2e1d154c3a7c4af64c536c30dbdb1b4bf5af01ab_2_200x140.jpeg"}], "tags": ["chuck-e-cheese", "lost-media", "aam"], "tags_descriptions": {}, "views": 460, "like_count": 5, "has_summary": false, "last_poster_username": "randomguyfan22-maker", "category_id": 5, "op_like_count": 5, "pinned_globally": false, "featured_link": null, "has_accepted_answer": false, "can_vote": false, "posters": [{"extras": null, "description": "Original Poster", "user_id": 1, "primary_group_id": 41, "flair_group_id": 41}, {"extras": null, "description": "Frequent Poster", "user_id": 27, "primary_group_id": 41, "flair_group_id": 41}, {"extras": null, "description": "Frequent Poster", "user_id": 12, "primary_group_id": 41, "flair_group_id": 41}, {"extras": "latest", "description": "Most Recent Poster", "user_id": 26, "primary_group_id": 41, "flair_group_id": 41}]}, {"fancy_title": "Peeler Rose Starts Pre-Sale for Chuck E. Cheese Comic", "id": 172, "title": "Peeler Rose Starts Pre-Sale for Chuck E. Cheese Comic", "slug": "peeler-rose-starts-pre-sale-for-chuck-e-cheese-comic", "posts_count": 2, "reply_count": 0, "highest_post_number": 2, "image_url": "https://forum.cheeseepedia.org/uploads/default/optimized/1X/bc7c19ba997a629a63a6a4bbe55750c2288c2e2e_2_736x1024.jpeg", "created_at": "2025-12-16T21:09:03.990Z", "last_posted_at": "2025-12-17T02:57:58.380Z", "bumped": true, "bumped_at": "2025-12-17T02:57:58.380Z", "archetype": "regular", "unseen": false, "pinned": false, "unpinned": null, "visible": true, "closed": false, "archived": false, "bookmarked": null, "liked": null, "thumbnails": [{"max_width": null, "max_height": null, "width": 1544, "height": 2146, "url": "https://forum.cheeseepedia.org/uploads/default/original/1X/bc7c19ba997a629a63a6a4bbe55750c2288c2e2e.jpeg"}, {"max_width": 1024, "max_height": 1024, "width": 736, "height": 1024, "url": "https://forum.cheeseepedia.org/uploads/default/optimized/1X/bc7c19ba997a629a63a6a4bbe55750c2288c2e2e_2_736x1024.jpeg"}, {"max_width": 800, "max_height": 800, "width": 575, "height": 800, "url": "https://forum.cheeseepedia.org/uploads/default/optimized/1X/bc7c19ba997a629a63a6a4bbe55750c2288c2e2e_2_575x800.jpeg"}, {"max_width": 600, "max_height": 600, "width": 431, "height": 600, "url": "https://forum.cheeseepedia.org/uploads/default/optimized/1X/bc7c19ba997a629a63a6a4bbe55750c2288c2e2e_2_431x600.jpeg"}, {"max_width": 400, "max_height": 400, "width": 287, "height": 400, "url": "https://forum.cheeseepedia.org/uploads/default/optimized/1X/bc7c19ba997a629a63a6a4bbe55750c2288c2e2e_2_287x400.jpeg"}, {"max_width": 300, "max_height": 300, "width": 215, "height": 300, "url": "https://forum.cheeseepedia.org/uploads/default/optimized/1X/bc7c19ba997a629a63a6a4bbe55750c2288c2e2e_2_215x300.jpeg"}, {"max_width": 200, "max_height": 200, "width": 143, "height": 200, "url": "https://forum.cheeseepedia.org/uploads/default/optimized/1X/bc7c19ba997a629a63a6a4bbe55750c2288c2e2e_2_143x200.jpeg"}], "tags": ["chuck-e-cheese"], "tags_descriptions": {}, "views": 204, "like_count": 2, "has_summary": false, "last_poster_username": "cmsentance-byte", "category_id": 5, "op_like_count": 2, "pinned_globally": false, "featured_link": null, "has_accepted_answer": false, "can_vote": false, "posters": [{"extras": null, "description": "Original Poster", "user_id": 1, "primary_group_id": 41, "flair_group_id": 41}, {"extras": "latest", "description": "Most Recent Poster", "user_id": 61, "primary_group_id": null, "flair_group_id": null}]}, {"fancy_title": "YouTooz Announces Christmas Special Chuck Plush", "id": 170, "title": "YouTooz Announces Christmas Special Chuck Plush", "slug": "youtooz-announces-christmas-special-chuck-plush", "posts_count": 12, "reply_count": 5, "highest_post_number": 12, "image_url": "https://forum.cheeseepedia.org/uploads/default/optimized/1X/4a2df5d8c3cd831499a6c05d43d02780127d410b_2_1024x1024.jpeg", "created_at": "2025-12-14T22:20:44.814Z", "last_posted_at": "2025-12-21T22:09:08.156Z", "bumped": true, "bumped_at": "2025-12-21T22:09:08.156Z", "archetype": "regular", "unseen": false, "pinned": false, "unpinned": null, "visible": true, "closed": false, "archived": false, "bookmarked": null, "liked": null, "thumbnails": [{"max_width": null, "max_height": null, "width": 1500, "height": 1500, "url": "https://forum.cheeseepedia.org/uploads/default/original/1X/4a2df5d8c3cd831499a6c05d43d02780127d410b.jpeg"}, {"max_width": 1024, "max_height": 1024, "width": 1024, "height": 1024, "url": "https://forum.cheeseepedia.org/uploads/default/optimized/1X/4a2df5d8c3cd831499a6c05d43d02780127d410b_2_1024x1024.jpeg"}, {"max_width": 800, "max_height": 800, "width": 800, "height": 800, "url": "https://forum.cheeseepedia.org/uploads/default/optimized/1X/4a2df5d8c3cd831499a6c05d43d02780127d410b_2_800x800.jpeg"}, {"max_width": 600, "max_height": 600, "width": 600, "height": 600, "url": "https://forum.cheeseepedia.org/uploads/default/optimized/1X/4a2df5d8c3cd831499a6c05d43d02780127d410b_2_600x600.jpeg"}, {"max_width": 400, "max_height": 400, "width": 400, "height": 400, "url": "https://forum.cheeseepedia.org/uploads/default/optimized/1X/4a2df5d8c3cd831499a6c05d43d02780127d410b_2_400x400.jpeg"}, {"max_width": 300, "max_height": 300, "width": 300, "height": 300, "url": "https://forum.cheeseepedia.org/uploads/default/optimized/1X/4a2df5d8c3cd831499a6c05d43d02780127d410b_2_300x300.jpeg"}, {"max_width": 200, "max_height": 200, "width": 200, "height": 200, "url": "https://forum.cheeseepedia.org/uploads/default/optimized/1X/4a2df5d8c3cd831499a6c05d43d02780127d410b_2_200x200.jpeg"}], "tags": ["chuck-e-cheese", "cec-animated-series"], "tags_descriptions": {}, "views": 221, "like_count": 3, "has_summary": false, "last_poster_username": "cmsentance-byte", "category_id": 5, "op_like_count": 1, "pinned_globally": false, "featured_link": null, "has_accepted_answer": false, "can_vote": false, "posters": [{"extras": null, "description": "Original Poster", "user_id": 1, "primary_group_id": 41, "flair_group_id": 41}, {"extras": null, "description": "Frequent Poster", "user_id": 12, "primary_group_id": 41, "flair_group_id": 41}, {"extras": null, "description": "Frequent Poster", "user_id": 7, "primary_group_id": null, "flair_group_id": 49}, {"extras": "latest", "description": "Most Recent Poster", "user_id": 61, "primary_group_id": null, "flair_group_id": null}]}, {"fancy_title": "Adventure World Removes its Dance Floor!", "id": 169, "title": "Adventure World Removes its Dance Floor!", "slug": "adventure-world-removes-its-dance-floor", "posts_count": 3, "reply_count": 1, "highest_post_number": 3, "image_url": "https://forum.cheeseepedia.org/uploads/default/optimized/1X/83761063f9d941bb6b0e8470095fbaef2f12657e_2_1024x576.jpeg", "created_at": "2025-12-14T20:50:01.484Z", "last_posted_at": "2026-01-19T14:11:40.928Z", "bumped": true, "bumped_at": "2026-01-19T14:11:40.928Z", "archetype": "regular", "unseen": false, "pinned": false, "unpinned": null, "visible": true, "closed": false, "archived": false, "bookmarked": null, "liked": null, "thumbnails": [{"max_width": null, "max_height": null, "width": 1280, "height": 720, "url": "https://forum.cheeseepedia.org/uploads/default/original/1X/83761063f9d941bb6b0e8470095fbaef2f12657e.jpeg"}, {"max_width": 1024, "max_height": 1024, "width": 1024, "height": 576, "url": "https://forum.cheeseepedia.org/uploads/default/optimized/1X/83761063f9d941bb6b0e8470095fbaef2f12657e_2_1024x576.jpeg"}, {"max_width": 800, "max_height": 800, "width": 800, "height": 450, "url": "https://forum.cheeseepedia.org/uploads/default/optimized/1X/83761063f9d941bb6b0e8470095fbaef2f12657e_2_800x450.jpeg"}, {"max_width": 600, "max_height": 600, "width": 600, "height": 337, "url": "https://forum.cheeseepedia.org/uploads/default/optimized/1X/83761063f9d941bb6b0e8470095fbaef2f12657e_2_600x337.jpeg"}, {"max_width": 400, "max_height": 400, "width": 400, "height": 225, "url": "https://forum.cheeseepedia.org/uploads/default/optimized/1X/83761063f9d941bb6b0e8470095fbaef2f12657e_2_400x225.jpeg"}, {"max_width": 300, "max_height": 300, "width": 300, "height": 168, "url": "https://forum.cheeseepedia.org/uploads/default/optimized/1X/83761063f9d941bb6b0e8470095fbaef2f12657e_2_300x168.jpeg"}, {"max_width": 200, "max_height": 200, "width": 200, "height": 112, "url": "https://forum.cheeseepedia.org/uploads/default/optimized/1X/83761063f9d941bb6b0e8470095fbaef2f12657e_2_200x112.jpeg"}], "tags": ["chuck-e-cheese", "bankruptcy-believers", "adventure-world"], "tags_descriptions": {}, "views": 171, "like_count": 1, "has_summary": false, "last_poster_username": "CECR995", "category_id": 5, "op_like_count": 1, "pinned_globally": false, "featured_link": null, "has_accepted_answer": false, "can_vote": false, "posters": [{"extras": null, "description": "Original Poster", "user_id": 1, "primary_group_id": 41, "flair_group_id": 41}, {"extras": null, "description": "Frequent Poster", "user_id": 7, "primary_group_id": null, "flair_group_id": 49}, {"extras": "latest", "description": "Most Recent Poster", "user_id": 65, "primary_group_id": 41, "flair_group_id": 41}]}, {"fancy_title": "Volo Releases New RAE Merch!", "id": 167, "title": "Volo Releases New RAE Merch!", "slug": "volo-releases-new-rae-merch", "posts_count": 1, "reply_count": 0, "highest_post_number": 1, "image_url": "https://forum.cheeseepedia.org/uploads/default/optimized/1X/e08267e154946a923d0cb007cbced3bdc82f29a2_2_1024x576.jpeg", "created_at": "2025-12-12T19:28:55.837Z", "last_posted_at": "2025-12-12T19:28:56.031Z", "bumped": true, "bumped_at": "2025-12-12T19:28:56.031Z", "archetype": "regular", "unseen": false, "pinned": false, "unpinned": null, "visible": true, "closed": false, "archived": false, "bookmarked": null, "liked": null, "thumbnails": [{"max_width": null, "max_height": null, "width": 1280, "height": 720, "url": "https://forum.cheeseepedia.org/uploads/default/original/1X/e08267e154946a923d0cb007cbced3bdc82f29a2.jpeg"}, {"max_width": 1024, "max_height": 1024, "width": 1024, "height": 576, "url": "https://forum.cheeseepedia.org/uploads/default/optimized/1X/e08267e154946a923d0cb007cbced3bdc82f29a2_2_1024x576.jpeg"}, {"max_width": 800, "max_height": 800, "width": 800, "height": 450, "url": "https://forum.cheeseepedia.org/uploads/default/optimized/1X/e08267e154946a923d0cb007cbced3bdc82f29a2_2_800x450.jpeg"}, {"max_width": 600, "max_height": 600, "width": 600, "height": 337, "url": "https://forum.cheeseepedia.org/uploads/default/optimized/1X/e08267e154946a923d0cb007cbced3bdc82f29a2_2_600x337.jpeg"}, {"max_width": 400, "max_height": 400, "width": 400, "height": 225, "url": "https://forum.cheeseepedia.org/uploads/default/optimized/1X/e08267e154946a923d0cb007cbced3bdc82f29a2_2_400x225.jpeg"}, {"max_width": 300, "max_height": 300, "width": 300, "height": 168, "url": "https://forum.cheeseepedia.org/uploads/default/optimized/1X/e08267e154946a923d0cb007cbced3bdc82f29a2_2_300x168.jpeg"}, {"max_width": 200, "max_height": 200, "width": 200, "height": 112, "url": "https://forum.cheeseepedia.org/uploads/default/optimized/1X/e08267e154946a923d0cb007cbced3bdc82f29a2_2_200x112.jpeg"}], "tags": [], "tags_descriptions": {}, "views": 162, "like_count": 1, "has_summary": false, "last_poster_username": "The-64th-Gamer", "category_id": 5, "op_like_count": 1, "pinned_globally": false, "featured_link": null, "has_accepted_answer": false, "can_vote": false, "posters": [{"extras": "latest single", "description": "Original Poster, Most Recent Poster", "user_id": 1, "primary_group_id": 41, "flair_group_id": 41}]}, {"fancy_title": "Food Theory Releases Death of CEC Video", "id": 166, "title": "Food Theory Releases Death of CEC Video", "slug": "food-theory-releases-death-of-cec-video", "posts_count": 1, "reply_count": 0, "highest_post_number": 1, "image_url": "https://forum.cheeseepedia.org/uploads/default/optimized/1X/7f67af65ba58e58a1874b32aaae787e80af5d033_2_1024x576.jpeg", "created_at": "2025-12-11T23:25:36.390Z", "last_posted_at": "2025-12-11T23:25:36.570Z", "bumped": true, "bumped_at": "2025-12-11T23:25:36.570Z", "archetype": "regular", "unseen": false, "pinned": false, "unpinned": null, "visible": true, "closed": false, "archived": false, "bookmarked": null, "liked": null, "thumbnails": [{"max_width": null, "max_height": null, "width": 1280, "height": 720, "url": "https://forum.cheeseepedia.org/uploads/default/original/1X/7f67af65ba58e58a1874b32aaae787e80af5d033.jpeg"}, {"max_width": 1024, "max_height": 1024, "width": 1024, "height": 576, "url": "https://forum.cheeseepedia.org/uploads/default/optimized/1X/7f67af65ba58e58a1874b32aaae787e80af5d033_2_1024x576.jpeg"}, {"max_width": 800, "max_height": 800, "width": 800, "height": 450, "url": "https://forum.cheeseepedia.org/uploads/default/optimized/1X/7f67af65ba58e58a1874b32aaae787e80af5d033_2_800x450.jpeg"}, {"max_width": 600, "max_height": 600, "width": 600, "height": 337, "url": "https://forum.cheeseepedia.org/uploads/default/optimized/1X/7f67af65ba58e58a1874b32aaae787e80af5d033_2_600x337.jpeg"}, {"max_width": 400, "max_height": 400, "width": 400, "height": 225, "url": "https://forum.cheeseepedia.org/uploads/default/optimized/1X/7f67af65ba58e58a1874b32aaae787e80af5d033_2_400x225.jpeg"}, {"max_width": 300, "max_height": 300, "width": 300, "height": 168, "url": "https://forum.cheeseepedia.org/uploads/default/optimized/1X/7f67af65ba58e58a1874b32aaae787e80af5d033_2_300x168.jpeg"}, {"max_width": 200, "max_height": 200, "width": 200, "height": 112, "url": "https://forum.cheeseepedia.org/uploads/default/optimized/1X/7f67af65ba58e58a1874b32aaae787e80af5d033_2_200x112.jpeg"}], "tags": ["chuck-e-cheese", "bankruptcy-believers"], "tags_descriptions": {}, "views": 154, "like_count": 2, "has_summary": false, "last_poster_username": "The-64th-Gamer", "category_id": 5, "op_like_count": 2, "pinned_globally": false, "featured_link": null, "has_accepted_answer": false, "can_vote": false, "posters": [{"extras": "latest single", "description": "Original Poster, Most Recent Poster", "user_id": 1, "primary_group_id": 41, "flair_group_id": 41}]}]}}